{
    "0": "H V9HD 06 29:55 giây",
    "10122": "H VIHD 06:39:02",
    "10227": "H V9HD 06:39:06 HÒA BÌNH: VẬN ĐỘNG VIÊN TỪ VONG TRONG LÚC CHẠY GIẢI SIÊU MARATHON VIỆT NAM",
    "10374": "H V9HD 06:39:12",
    "10493": "H V9HD 06:39:17",
    "10577": "V9HD 06:39:20",
    "10605": "H VIND 06:39:21",
    "10661": "V9HD 06:39:23",
    "10668": "VIND 06:39:24 TRAVEL VUM IOHN FIRST ED TIOI",
    "10689": "V9HD 06:39:25 VUM TONH",
    "10745": "H V9HD 06:39:27",
    "10787": "H V9HD 06:39:28",
    "10808": "V9HD 06:39:29",
    "10822": "V 9HD 06:39:30",
    "10850": "V9HD 06:39:31 NH S",
    "10906": "V9HD 06:39:33 INH",
    "10976": "HT V9HD 06:39:36 VUML Editiou VIETNAM ULTRA MARATHON Editiou 1st VUM HOKA VUM UM VUM VUM U VUMT /UM VIIM",
    "11263": "06:20 06:39:48 VUMX Editiou VIETNAM ULTRA MARATHON Editiou VUM HOKA HOKA UM UM DASPORT UMI VII",
    "11501": "H V THD 06:39:57",
    "1162": "H V9HD 06:30:42",
    "11788": "H VINHD 06:40:09 SAINH T!",
    "11879": "V9HD 06:40:12 SÀ LAN VA CHẠM LÀM LỆCH NHỊP CẦU QUA SÔNG CẦN THƠ",
    "11991": "06:40 H V9 HD HINO",
    "12054": "H V 9HD 06:40-19",
    "12117": "V 9HD 06.40.22",
    "12159": "06.40:23 H V O HD HINO",
    "12222": "06:40:26 H V 0 HD 27210 95-H1",
    "12250": "HT V9HD 06:40:27",
    "12264": "V9HD 06.40.28",
    "1232": "H V9HD 06:30 44 XÂM NHẬP MẶN TIẾN SÂU TRỞ LẠI",
    "12355": "H V9HD 06.40.31",
    "1239": "H V9HD 06:30:45 giay XÂM NHẬP MẶN TIẾN SÂU TRỜ LAI",
    "12460": "H 9HD 06.40:35",
    "12551": "H V 9HD 06:40:39",
    "12621": "V9HD 06:40: 42",
    "12705": "HINHO 06:40:45",
    "12775": "HTV9 06 40 48 giây",
    "1288": "06.30.47 HD giay XÂM NHẬP MẶN TIẾN SÂU TRỜ LAI",
    "13097": "H V9HD 06:41:01",
    "13139": "06:41:03 V9 HD",
    "13188": "06:41:05 H VO HD HẬU GIANG: BÁT NHÓM ĐÔI TƯỢNG CHUYÊN TRỘM VỎ LÃI XUỐNG MÁY",
    "13237": "End 06:41:06 HẬU GIANG: BÁT NHÓM ĐÔI TƯỢNG CHUYÊN TRỘM VÕ LÃI giày XUỐNG MÁY",
    "13279": "06:41:08 H HD HẬU GIANG: BÁT NHÓM ĐÔI TƯỢNG CHUYÊN TRỘM VÕ LÃI XUỐNG MÁY",
    "13342": "H V9HD 06:41:11",
    "1337": "H V %HO 06:30:49 XÂM NHẬP MẶN TIẾN SÂU TRỞ LAI",
    "13377": "H V9HD 06:41:12",
    "13419": "H V9HD 06:41:14",
    "13475": "H VINH 06.41:16 SIE",
    "13531": "H 19HD 06:41:18 NO Sturn Vie NOOAL 511",
    "13580": "H VIND 06:41:20",
    "1365": "H VIHD 06:30:50",
    "13657": "9RD 06-41-23",
    "13720": "06:41:26 H V HD",
    "1379": "V9HD 06:30:50",
    "13811": "H V %HD 06.41:29",
    "13839": "06:41:31 H THD",
    "13916": "V 9HD 06:41:34 HINOTA",
    "14": "V EHO 06:29:56 giây",
    "14028": "V9HD 06.41:38 83 SUC NG",
    "14049": "06:41:39 V9 HD",
    "14112": "H V9 06474",
    "1414": "V End 06-30:52",
    "14203": "THO 06:41:45",
    "14504": "V9HD 06:41:57",
    "14602": "H V9HD 06:42:01 Số: COQUANCÁNHSÁT 24 CÔNG QĐ AN VPCQCSĐT TỈNH ĐỒNG ĐIỀU THÁP TRA CỘNG Độc HÒA lập XÃ HỘI Tyrdo- CHỦ Hạnh NGHĨA B3Thao771920202T.8.80 phúc qư VIETNAM (972/202/ Mhush Họ Căn tháng Căn cú kết cứ 3 năm quà Quyết 2024 PHÓ định của khới Ca THỦ tô CÔNG TRƯỜNG QUYẾT vụ an AN hình ĐỊNH CƠ TỈNH QUANCÁNH KHỞI ĐỒNG Đồng TÓBỊCAN THÁP Tháp SÁTĐIEUTRA ngày22thang 3năm 2024 ĐỒNG THÁP: BẮT ĐỐI TƯỢNG ĐÂM CHẾT VỢ HỞ SAU KHI CÙNG SỬ DỤNG MA TUÝ nam",
    "14672": "V9HD 06:42:04 ĐỒNG THÁP: BẮT ĐÔI TƯỢNG ĐÂM CHẾT VỢ HỜ giày SAU KHI CÙNG SỬ DỤNG MA TUÝ",
    "14728": "V9HD 06: 42:06",
    "14819": "V9HD 06 42:10",
    "14882": "06.42:12 H V 9 HĐ",
    "1491": "H VIND 06:30:56",
    "14952": "Quốc Sinhngày tịch Tengoikhic: 25thing Hotbn:HỒ 17tháng 12năm Tamgiam hình 7nẩm Thanh SỰ 2024đoi Hình trong ChocuĐiều Hồ Phong: SỰ thang3năm VỚI Thanh thờihan Giới bị Cản can. tinh: Phong 30 117 củ Điểu 2024cla ngày đặcó Quyết Số COQUANCÁNHSÁT 109 RALỆNH: hành ketừngày dịnh Coquan CÔNGANTINHĐÔNG PHÓ khoản /LTG-VPCQCSĐT VÌ khoi THƯ Cánh Giếtngười / Điểu 23 tổ CÔNGANTINH TRƯỜNGCOQUANCANH.SAT bị tháng sitdiều 119 can ĐIỀU phạm và LENHTẠMGIAM tra sbaLlmuQp-VPCOCSDT. THÁP TRA Điểu vào Công 173 khoản ĐỒNG an Bộ tinh CỘNG / THÁP luật Đồng ĐồngTháp Điều Độclịp HÒA Tó 123 Tháp tụng XÀHỌICHÙ ĐIỀUTRA Bộluột ngày ngdyst-shing Tựdo đổivải Sol Hạnh NGHĨA MỲT phúc 06:42:15 H VIETNAM 2024 Mhanh VIND",
    "15015": "H V9HD 06:42:18 Thanh Guong chuán Thật Thật TỊU xethex Dóng yuà TRƯONG / yun op hành Thap thi THU OHD",
    "15064": "V9HD 06:42:20",
    "15141": "06-42.23 THD",
    "15176": "064 HĐ",
    "15183": "VINH 06:42:24",
    "15197": "H V9HD 06:42:25 O",
    "15211": "HTV9 06:42:25 giây TIEPTHEO",
    "15239": "06 H 42:27 V9 HD",
    "15253": "06 H 42:27 V9 HD VIDEO VỤ TẤN CÔNG KHÙNG BỐ MATXCOVA",
    "15302": "TIẾP THEO 06 H 42:29 V9 HD 3/ 2024 Cutu Xoan VIDEO VỤ TẤN CÔNG KHÙNG BỐ MATXCOVA",
    "15351": "TIẾP THEO 06: H 42.31 V9 HD VIDEO VỤ TẤN CÔNG KHÙNG BỐ MATXCOVA",
    "15414": "V9HD 06:42:34",
    "15428": "V9HD 06:42:34 50 NĂM PHÁT SÓNG BỘ PHIM \"NGÔI NHÀ NHỎ TRÊN THẢO NGUYÊN\"",
    "15470": "V9HD TIẾP THEO 06:42:36 50 NĂM PHÁT SÓNG BỘ PHIM \"NGÔI NHÀ NHỎ TRÊN THẢO NGUYÊN\"",
    "15498": "H V 9HD TIẾP THEO YARDAGE 06.42:37 TANCE&PLAIN 50 NĂM PHÁT SÓNG BỘ PHIM \"NGÔI NHÀ NHỎ TRÊN THẢO NGUYÊN\" USTRE STAN",
    "1554": "H VIND 06:30:58",
    "15540": "H V9HD TIẾP THEO 06:42:39 50 NĂM PHÁT SÓNG BỘ PHIM \"NGÔI NHÀ NHỎ TRÊN THẢO NGUYÊN\"",
    "15575": "H V IND TIẾP THEO 06:42:40 50 NĂM PHÁT SÓNG BỘ PHIM \"NGÔI NHÀ NHỎ TRÊN THẢO NGUYÊN\"",
    "15617": "064.42:42 V9 HD",
    "15624": "06:52-42",
    "15631": "H V9HO 06:42:42",
    "15638": "06:42:43 V9 HD",
    "15645": "H V9 06 42:43 giây",
    "15673": "06: 45:06 V9 HD giây",
    "16009": "06:45: H V9 19 HD",
    "16093": "06: H 45:23 V9 HD 22/ 03/ 2024 Kpokyc CUTN Xonn KtrllSmotoaninou VIDEO VỀ VỤ TẤN CÔNG KHÙNG BỐ giay Ở TRUNG TÂM HÒA NHẠC CROCUS NGA",
    "16128": "06: H 45:24 V9 HD 22/ 03/ 2024 Kpokyc CUTN Xonn #KarlSmolyanomanh VIDEO VỀ VỤ TẤN CÔNG KHÙNG BỐ giáy Ở TRUNG TÂM HÒA NHẠC CROCUS NGA",
    "16184": "06 H 45: 26 V9 HD 22/ 03/ 2024 Kpokyc CUTN Xonn @KinlSmolyanmou VIDEO VỀ VỤ TẤN CÔNG KHÙNG BỐ Ở TRUNG TÂM HÒA NHẠC CROCUS NGA",
    "16233": "06: H 45:28 V9 HD 22/ 03/ 2024 Kpokyc CNTN Xonn chillSmolanenou",
    "16268": "06 H 45: 30 V9 HD 03/ 2024 KpoKyC CUTN Xonn @KinllSmolyanm.mu",
    "1631": "H VIND 06:31:01",
    "16324": "06 H 45:32 V9 HD MÌ 22/ 03/ 2024 KP KYC CUTN Xonst a KinllSmolvanmouru",
    "16331": "06 45:32 V9 HD 22/ 03/ 2024 Kpokyc CUTN Xonn @KirliSmokanhou",
    "16345": "06 H 45:33 V9 HD 22/ 03/ 2024 Kpokyc CUTN Xonn O lyaninoy",
    "16380": "06 H 45:34 V9 HD 22/ 03/ 2024 Kpokyc CUTN Xonn O KinHSmotranmon",
    "16415": "06 H 45.36 V9 HD O KirliSmoivantnoy",
    "16429": "06 H 45:36 VO HD KtrilSmolvaninov",
    "16457": "06 H 45:37 VO HD (KiriSmoluanipou",
    "16527": "06:45: H 40 V9 HD (Kirill Smolyaninov",
    "16534": "06 H 45 40 V9 HD 6 irillSmo Ivanmoy",
    "16569": "06:45:42 H V9 HD KallSnolyaniou",
    "16597": "H V EHO 06:45:43",
    "1687": "06:31:04 H V9 HD",
    "16961": "0645 HD",
    "17010": "IHD 06:45:59",
    "17094": "H V9HD 06:46:03",
    "17171": "06146:06 V9 HD DRAGON giày KINH TẾ THÁI LAN ĐỐI MẶT NGUY CƠ SUY THOÁI DÀI HẠN",
    "17297": "FONEARNCLINE MARKET Joues' Sal 06:46 11 V 9 HD I IN",
    "17430": "06:46:16 V 9 HD we",
    "1750": "CHƯƠNG TRINHGIGIAY 18:30 TRÊN HTV H H VIND 06:31:06",
    "17556": "06:46:21 H V9 HD GC SUPERCENTER THE NEW",
    "17647": "06:46:25 V9 HD AVEDA 10%",
    "17703": "ANHOIHE ANOTHER TROT2 STORY H V9HD 06:46:27 PARAGON HANZ DE FUK 1 MG",
    "17773": "06.46.30 H Q HD",
    "17822": "06.46: H 32 V9 HD LABANO",
    "17892": "06.46:35 H V9 HD WINH Gi NX70",
    "17927": "ĐUNHN 06.46.36 H V9 HD",
    "17976": "06.46:38 V9 HD TIESTA ER 0109716",
    "1806": "CHƯƠNGTRINH.CHÁY 18:30 TRÊN TV7 H V9HD 06.31:08",
    "18060": "13 GULAN muộp Day 06:46:41 V9HD SAVE",
    "18123": "V9HD 06:46:44",
    "18186": "VINH 06:46:46",
    "18200": "06:46:47 H V9 HD",
    "18207": "H V9HD 06:46:47",
    "18291": "H VIND 06.46:51",
    "18529": "H V9HD 0647:00",
    "18578": "H V9HD 06:47:02",
    "18585": "H V9HD 06:47:02 giáy BẢO ĐỔ BỘ VÙNG ĐÔNG BẮC MỸ KÈM THEO TUYẾT RƠI DÀY",
    "18606": "V9HD 06:47:03 BẢO ĐỔ BỘ VÙNG ĐÔNG BẮC MỸ KÈM THEO TUYẾT RƠI DÂY",
    "18683": "V9HD 06:47:06 BẢO ĐỔ BỘ VÙNG ĐÔNG BẮC MỸ KÈM THEO TUYẾT RƠI DÀY",
    "18718": "06.47:08 HD VERMON GIFT",
    "18802": "9HD 06.47:11",
    "18844": "06.47.13 H HD",
    "18858": "H V9HD 06:47:13",
    "1890": "CHƯƠNG TRÌNH 60 GIÂY 18:30 TRÊN H V END 06:31:12",
    "18928": "06:47:16 V9 HD",
    "19005": "H V9HD 06:47:19",
    "19019": "06:47:20/ V9 HD SUORE FANAY",
    "1904": "EHD 06:31:12 169 29 - O",
    "19061": "06:47:21 H V 9 HD SUORLO INH",
    "19152": "HTVỌ",
    "19215": "H V9RD 06:47:28",
    "19236": "VIHD 06:47:28 CỌ 43 Y 00 FEET ONLY",
    "19243": "V9HD 064729 giãy",
    "19299": "H VIND 06.47.31",
    "19334": "H V 9HD 06:47:32 glày",
    "19348": "H V9HD 06:47:33",
    "19369": "V9HD 064734",
    "19376": "V 9HD 06:47:34",
    "19404": "V9HD 06:47:35",
    "19432": "V9HD 06:47:36",
    "19446": "V9HD 06:47:37",
    "19481": "V9HD 06:47:38",
    "19516": "V 9HD 06.47:40",
    "19551": "V9HD 0647.41",
    "19558": "H V9HD 06:47:41",
    "19600": "V9ND 06:47:43",
    "19635": "VIHD 06:47:44 BỘ PHIM NGÔI NHÀ NHỎ TRÊN THẢO NGUYÊN\" KÝ NIỆM SINH NHẬT LẦN THƯ 50 NĂM",
    "19656": "V9HD 06:47:45 BỘ PHIM NGÔI NHÀ NHỎ TRÊN THẢO NGUYÊN\" KỲ NIỆM SINH NHẬT LẦN THỨ 50 NĂM",
    "1967": "06.31.15 H V9 HD",
    "19691": "H V 9HD 06.47:47 YARDAGE FANCY&PLAIN DECREATEST HINKLE BỘ PHIM \" NGÔI NHÀ NHỎ TRÊN THẢO NGUYÊN\" KÝ NIỆM SINH NHẬT LẦN THỨ 50 NĂM USIRE STAN",
    "19747": "H VIHD 06:47:49 BỘ PHIM NGÔI NHÀ NHỎ TRÊN THẢO NGUYÊN\" KÝ NIỆM SINH NHẬT LẦN THỨ 50 NĂM",
    "19775": "V9HD 06:47:50",
    "19782": "V9HD 06:47:50",
    "19796": "V9HD 06:47:51",
    "19838": "V9HD 06:47:53",
    "19873": "H VIND 06:47:54",
    "19901": "H VIHD 06:47:55",
    "19915": "V9HD 06:47:56 KATHY ESTRADA và KRISTIE HERNANDEZ",
    "20006": "V 9HD 0647:59",
    "20041": "V9HD 06-48:01",
    "20062": "VIHD 06-48:01 KATHRYN WALSH NGƯỜI HÂM MỘ",
    "20174": "06:48-06 V9 HD",
    "20181": "H V9HD 06:48:06 Lattee Faura House CARRE BAYON McCALLS VILLY TOBBILS AND CARRIE Rag-Doll",
    "20230": "V9HD 06:48:08 Little House on the Prairie Calendar 1977",
    "20251": "H V9HD 06:48:09",
    "20286": "V 9HD 06:48:10",
    "20321": "V9HD 06:48:12",
    "20328": "H V9HD 06:48:12 JUNATOS",
    "2037": "H V9HD 06:31:18",
    "20377": "VIND 06:48:14",
    "20405": "V9HD 06:48:15",
    "20447": "V9HD 06:48:17 MICHAEL LANDON JR giáy CON TRAI CỦA MICHAEL LANDON",
    "20580": "V9HD 06:48:22",
    "20811": "H V9HD 06:48:31",
    "20867": "06 8 34 HD",
    "20881": "06: 48.34",
    "20909": "V9HD 06:48:35",
    "2093": "06:31:20 10 HĐ",
    "20979": "H V 9HD 06:48:38",
    "20993": "H THD 06:48:39",
    "21014": "V9HD 06:48: 40",
    "21049": "V9HD 06:48:41",
    "21056": "06.48.41 H V 9 HD giây",
    "21112": "H V9HD 06:48:43",
    "21168": "H EHD 06:48:46",
    "21259": "HTV9 06:48: 49",
    "21315": "HTV9 06:48:52",
    "21399": "HT V9HD 06:48:55 JOLIA",
    "21434": "H V9HD 06:48:56",
    "21455": "H V9HD 06.48:57",
    "21532": "H V9HD 06:49:00 NGƯỜI ĐI CÂU Ở PARIS: CHẤT LƯỢNG NƯỚC SÔNG SEINE ĐƯỢC CẢI THIỆN",
    "21602": "H V9HD 06:49:03 NGƯỜI ĐI CÂU Ở PARIS: CHẤT LƯỢNG NƯỚC SÔNG SEINE ĐƯỢC CẢI THIỆN",
    "21651": "V9HD 06:49:05",
    "21679": "H V9HD 06:49:06",
    "21735": "V9HD 06:49:08",
    "21770": "06:49:10 H V 9 HD BILL FRANCOIS NHÀ VĂN SAY MÊ CÂU CÁ",
    "21889": "H V9HD 06:49:15 giáy",
    "21917": "H VINH 06.49:16",
    "22015": "06:49:20 HD",
    "22064": "IGI H V9HD 06.49:22 JOLL",
    "22085": "IGI H V9HD 06:49:22 THỂ",
    "22148": "H V9HD 06 49:25 JOLIA",
    "22190": "H V9HD 06:49:27",
    "22253": "H V9HD 06:49:29",
    "22302": "H V9HD 06:49:31 P15281F 1841120",
    "22351": "H V9HD 06:49:33",
    "22449": "H V 9HD 06.49:37",
    "22526": "06:49-40 H V9 HD",
    "22596": "06:49:43 H V9 HĐ",
    "22687": "V 9HD 06.49:46 giây",
    "22736": "H 9HD 06:49:48 69 giả",
    "22743": "06.49.49 9 HD 69",
    "22757": "H V9HD 06:49: 49 CAFES",
    "22764": "H V9HD 06:49:50 69",
    "22778": "H SOHD 06.49:50 69",
    "22848": "V9HD 06-49:53",
    "22897": "HTV910 06:49:55 184",
    "22988": "06:49:59 9 HD",
    "23016": "06:50:00 H V9 HD",
    "2303": "H 97AHD 06:31:28",
    "23051": "COURSE H V9HD AF ES 06:50:01 COURSE",
    "23100": "COURSE \"CA H V9HD 06:50:03 KHÔI PHỤC cuộc ĐUA DÀNH CHO CÁC NHÂN VIÊN BỐI BẢN SAU 13 NĂM GIÁN ĐOẠN",
    "23170": "06-50 06 V9 HD KHÔI PHỤC cuộc ĐUA DÀNH CHO CÁC NHÂN VIÊN BỐI BẢN SAU 13 NĂM GIÁN ĐOẠN",
    "23219": "06:50:08 THO 69 CAFES KHÔI PHỤC cuộc ĐUA DÀNH CHO CÁC NHÂN VIÊN BỔI BẢN SAU 13 NĂM GIÁN ĐOẠN",
    "23226": "06.5008 THÁ 69 CAFES",
    "23233": "06:50 08 9 HD TH SH 69 CAFE-",
    "23261": "06:50:09 H V9 HD COUR SÉC 69",
    "23275": "06:50:10 H V 9 HD CONH 69 CAFES",
    "23296": "RESTAURANT VIZHO 06:50:11",
    "23352": "H V9HD 06.50.13 216",
    "23387": "H VIHD 06:50-14 202",
    "23401": "V9HD 06.5015",
    "23415": "V 9HD 06.5016",
    "23464": "V9HD 06:50:18 Laune",
    "23485": "V9HD 06:50:18",
    "23499": "06:50:19 HTV9 HD",
    "23506": "V9HD 06:50:19",
    "23548": "H V9HD 06 50:21",
    "23555": "V 9HD 06-50:21",
    "23562": "06:50:21 V E HD",
    "23583": "VIND 06:50 22",
    "23632": "V9ND 06:50.24",
    "23667": "VIHD 06:50:26",
    "23702": "06:50:27 H V9 HD",
    "23730": "H V9HD 06:50:28",
    "23737": "V9HD 06:50:28",
    "23765": "YAMA H VOHD 06:50:30",
    "23786": "V9ND 06:50:30 167",
    "2380": "H V EHD 06:31:31",
    "23821": "06:50: H 32 V9 HD",
    "23842": "06:50:33 V9 HD Jeau COURSE LA GHR US de Paris \"CAFES",
    "23856": "V9HD 06:50:33 COI \"C PAR 67",
    "23884": "GES CAFES 06.50.34 9 HD URSE COURSE CAFES 167",
    "23905": "COURSE H V9HD \"CAFES 06:50:35 URSE COURSE 167",
    "23912": "V9HD 06.50: 35 IR 39",
    "23933": "06-50-36 V Ọ HD 39",
    "23975": "H V9HD 06-50:38 all 76 \"CAFES",
    "24003": "H V9HD 06:50:39 IR 76",
    "24017": "V9HD 06.50.40",
    "24052": "V9HD 06.50.41",
    "24080": "06:50:42 V9 HD",
    "24094": "LA V9HD 06:50:43",
    "24157": "H V9HD 06:50:45",
    "24171": "H V9HD 06:50:46",
    "24192": "H 9HD 06:50:47 VANHO",
    "24248": "H V 9HD 06:50:49",
    "24304": "H V9HD 06:50:51",
    "24388": "H VIHD 06-50-55",
    "24444": "V 9HD 06:50-57",
    "24514": "V9HD 06:51:00",
    "24570": "V 9HD 06:51:02 A2/50",
    "24619": "V 9HD 06:51:04",
    "24640": "06-51405 VIHD",
    "24689": "06-51-07 HD",
    "24752": "INƯONG MỸ 06:51:09 DONH TOP ĐÀ NĂNG: ĐÔI THAY Ở BẢO TÀNG ĐẼ NGÀY CÀNG HÚT KHÁCH THAM QUAN",
    "24815": "06.51.12 HD ĐÀ NẴNG: ĐÔI THAY Ở BẢO TÀNG ĐỂ NGÀY CÀNG HÚT KHÁCH THAM QUAN",
    "24850": "V9HD 06.51:13",
    "24920": "06: 51.16 V9 HD",
    "24983": "V9HD 06:51:18",
    "25025": "06:51:28 H V9 HD",
    "25102": "EHD 06: 51-23 giay DU KHÁCH MỸ",
    "25158": "9HD 06-51 25",
    "25214": "V9HD 06.51.28",
    "25410": "MUSEUM 06.51.35 V OF HD BẢO TÀNG",
    "25438": "H VIND 06.51:37",
    "25452": "06-51.37 V 9 HD",
    "25459": "06-51.37 H V OF HD",
    "25473": "06.51:38 H V 9 HD",
    "25480": "065138 H V 9 HD",
    "25515": "V9HD 06:31:40 A2/50",
    "25550": "06:51:41 HD",
    "25585": "06-51:42 V HD",
    "25613": "06:51.44 H V9 HD",
    "25634": "06:51:44 H VI HĐ",
    "25662": "06:51-45 H 9 HĐ",
    "25690": "VIHD 06 51:47",
    "25725": "V8HD 06 51: 48 Chị QUẢN NGUYỄN LÝ BẢO TÀNG THỊ DUYÊN KÝ ỨC ĐIÊU KHẮC ĐÁ MỸ NGHỆ NON NƯỚC TP ĐÀ NẴNG",
    "25795": "H V9HD 06:51:51 0",
    "25816": "V9HD 06:51:52",
    "25823": "H V9HD 06:51:52 O",
    "25865": "H V9HD 06:51:54",
    "25872": "V9HD 06.51:54",
    "25907": "H VIHD 06:51.55",
    "25935": "EHD 06:51:56",
    "25970": "H V THD 06:51:58",
    "26012": "# 06-51:59 V9HD",
    "26054": "H V9HD 06:52:01",
    "26103": "06:52:03 H 0 HD",
    "26152": "HTV9 06 52:05 Bóng của thị thành tập7",
    "26243": "H V9HD 06:52:09 TẬP 7 \"BÓNG CỦA THỊ THÀNH\": LỜI ĐỂ NGHỊ",
    "26313": "HTV9 06:52:12 TẬP 7 \"BÓNG CỦA THỊ THÀNH\": LỜI ĐỂ NGHỊ",
    "26397": "06:52:15 H V9H HD Bóng của thi thành tập7",
    "26467": "H V9HD 06:52:18",
    "26474": "H V9HD 06:52:18 Bóng của thi thành tập7",
    "26586": "H V9HD 06: 52:22 Bóng của thi thành tập7",
    "26677": "H V9HD 06:52:26",
    "26684": "HTV9 06:52:26 Bóng cua thi thành tập7",
    "26831": "V9HD 06:52:32 Bóng của thị thành tập7",
    "26908": "H V9HD 06:52:35 Bóng của thị thành- tập7",
    "2695": "9HD 06:31: 44",
    "27048": "V 9HD 06:52:41 BONG thi cúa Trà nh 1963025/01 2024",
    "27062": "V 9HD 06:52:41 BONG thi cúa TI hành 19G30 25/03/2024 V7",
    "27174": "06:52:46 V9 HD thi T ành TẬP 7 V7",
    "27181": "H V 9HD 06:57:28 giây",
    "27195": "H V 9HD 06:57-28 giây",
    "27202": "H V 9HD 06:57-29 giây",
    "27216": "H 9HD 06:57.29 giây",
    "27223": "H V9HD 06:57: 29 gia",
    "27230": "H V9HD 06:57:30",
    "27237": "HTV97- 06:57:30",
    "27244": "H V9HD 06.57.30",
    "27251": "HTV97:30 06:57:30",
    "27258": "H V9HD 06:57:31",
    "27265": "06:57:31 H V9 HD",
    "27272": "H V9HD 06: 57:31",
    "27279": "H V9HD 06:57.32",
    "27286": "HTV932 06:57",
    "27300": "H TV9HD 06:57",
    "27307": "06:57:33 H V9 HD HONOR",
    "27314": "V9HD 06:57 33 ALIZED 1",
    "27321": "H V 9HD 06-57:33",
    "27335": "H VIND 06:51:34 UATO",
    "27342": "06:57:34 H V9 HD",
    "27356": "H TV9HD 06.57:35 ford SPECIALIZED HONOB 96",
    "27363": "H BEHD 06:57:35 Ford SPECIALL",
    "27398": "H V IHD 06-57:36",
    "27405": "H V 9RD 06-57.37",
    "27440": "H IND 06:57-38",
    "27468": "06.57-39 H V9 HD",
    "27482": "H V9HD 06:57:40",
    "27489": "V9HD 06:57:40",
    "27517": "H VIHD 06:57:41",
    "27524": "H V9HD 06:57:41",
    "27552": "H V9HD 06:57:43",
    "27566": "V 9HD 06:57 43",
    "27580": "06:57: 44 V9 HD GIẢI ĐUA XE ĐAP ĐỖ DỐC: DANH HIỆU CAO NHẤT THUỘC VỀ TAY ĐUA COLOMBIA",
    "27601": "06!57: 44 V9 HD GIẢI DANH ĐUA HIỆU XE CAO ĐẠP NHẤT ĐÔ DỐC: THUỘC VỀ TAY ĐUA COLOMBIA",
    "27629": "V9HD 06:57: 46 GIẢI DANH ĐUA HIỆU XE CAO ĐẠP NHẤT ĐÔ DỐC: THUỘC VỀ TAY ĐUA COLOMBIA",
    "27636": "H V9HD 06.57.46 Mibil GIẢI ĐUA XE ĐAP ĐỖ DỐC: DANH HIỆU CAO NHẤT THUỘC VỀ TAY ĐUA COLOMBIA",
    "27692": "06:5748 HD GIẢI ĐUA XE ĐAP ĐÔ DỐC: DANH HIỆU CAO NHẤT THUỘC VỀ TAY ĐUA COLOMBIA",
    "27706": "V9HD 06:57: 49 GUANAJUATO",
    "27720": "ALHIUNDION V 9HD 06:57: 49 ford HONOR",
    "27783": "H V9HD 06.57:52",
    "27797": "H V9HD 06:57:52",
    "27818": "H V9HD 06:57:53",
    "27832": "H V9HD 06:57:54 RedBul TedBall Camex SPECIALIFED T",
    "27867": "H V9HD 06:57:55 RedBall Red BU",
    "27881": "H V9HD 06:57:56",
    "27895": "ER H V9HD STOP 06:57:56 STREM",
    "27923": "V THD 06:57:57 R",
    "2793": "V 9HD 06:31 48 KIÊN GIANG: CHÀNG TRAI 9X CHẾ MÔ HÌNH MÁY BAY CHIẾN ĐẦU SU- 35 CHAY TRÊN NƯỚC",
    "27944": "oume V9HD 06:57:58 SPECIALIZED Comex KARCHER OXXO Nazil",
    "27972": "06:57:59 HD Nozil",
    "27986": "V9HD 06:58:00",
    "27993": "H VIHD 06:58:00",
    "28": "06-29:56 HD giây",
    "28000": "DO 06.58-00",
    "28014": "HTV9 06:58:01",
    "28021": "H V9HD 06:58:01",
    "28056": "H V9HD 06:58:03 SPLIT TIME",
    "28070": "06:58:03 HD",
    "28077": "06:58:04 V 9 HD",
    "28084": "H VIHD 06-58-04",
    "28098": "H DAHD 06:58: 04",
    "28105": "V9HD 06:58:05 DE",
    "28112": "H VINH 06.58:05",
    "28119": "H V 9HD 06:58 05 0",
    "28126": "H TVINHO 06:58 05 ODPONS",
    "28140": "VIND 06:58:06 HONOR Yin SPITABLIS",
    "28147": "HTV9 06:58:06",
    "28210": "H V9HD 06:58 09",
    "28224": "H V9HD 06:58:09",
    "28245": "V9HD 06:58: 10",
    "28259": "SKI 06:58:11 H V9 HD AGL 0 ABull Redeal",
    "28287": "PUBLICAL AVE V9HD 06:58:12 C",
    "28308": "H V9HD 06:58:13",
    "28336": "H V9HD 06:58:14 GROPOO come",
    "28364": "H V 9HD 06-59:23 giây",
    "28399": "06:59:24 V 9 HD giây",
    "28406": "H V9HD 06:59:24 MUSADA QUE",
    "28413": "H V9HD MUBAD A 06:59:25 FACLE",
    "28448": "H V9HD 06:59:26",
    "28462": "H V9HD 06:59:27",
    "28476": "H V9HD 06:59:27",
    "28483": "H V9HD 06:59:28 CRICLE HOAL SALOP 13 All",
    "28497": "06:59:28 V9 HĐ- ORACLE ADALA HOLE SALOP",
    "28511": "H V9HD 06:59+29 BADALA ORACLE SALOP O",
    "28518": "H V9HD 06:59:29 SADALA ORACLE SALOP el",
    "28532": "HTV9 CẢI 06:59:29 SADAL ORACLE HOLEX SALOP",
    "28574": "H V9HD oar ORACLE 06:59:31 Nnear ORACLE ORACLE Nnear CLE 4 ORACLE START ORACLE",
    "28581": "H V 9HD ear ORACLE 06:59:31 Nnear ORACLE Nnear ORACLE Nnear CLE 4 ORACLE START K ORACLE km/h",
    "28602": "RC H V9HD 06:59:32 ORACLE",
    "2863": "9HD 06:31:51 PE KIÊN GIANG: CHÀNG TRAI 9X CHẾ MÔ HÌNH MÁY BAY CHIẾN ĐẦU SU- 35 CHAY TRÊN NƯỚC",
    "28658": "RC HT V9HD 06:59:35 DRACLE NEW ZEALAND VỀ NHẤT VÒNG 9 giay GIẢI ĐUA THUYỀN BUÔM HAI THÂN THẾ GIỚI",
    "28665": "ACLE ROLEX 3s Mnea START ORACLE Nnear ORACLE 06.59.35 V9 Nnear OI ORACLE + START + NEW ZEALAND VỀ NHẤT VÒNG 9 GIẢI ĐUA THUYỀN BUÔM HAI THÂN THẾ GIỚI",
    "28728": "ROLEX Os START Nnear 06.59.37 HOCLE im ORACLE + START + NEW ZEALAND VỀ NHẤT VÒNG 9 GIẢI ĐUA THUYỀN BUỔM HAI THÂN THẾ GIỚI",
    "28770": "ROLEX Os START Nnear 06:59:39 H V 9HD OI ORACLE + OR",
    "28798": "RACE START GP TRADEFUT BFR Os 06: 59 40 V 9HD A AUS SA: SAL GP SUI GER CAN",
    "28945": "cognizant LAPEX cognizant 48.7kmh 57.9km/h LAPEX 06:59 46 V 9 HD cognizant 300",
    "29078": "V 9HD 06:59:51 cognizant LAPEX cognizant LAPEX 45 2km/h cognizant LAPEX 77.5km/h cognizant 300 C 48. 3knh",
    "29092": "V9HD 06:59:52 83.2kmm FINISH SAILOP",
    "29176": "VIHD 06:59:55 BLACK POILS VEUCEAN GP CHRISTCH ROH",
    "2919": "H 9HO 06.31.53",
    "29232": "06:59:57 V 9 HD XK N7L",
    "29302": "V9HD 07:00:00 O",
    "29358": "H V9HD 07:00:03 giây",
    "294": "H V9HD 06:30:07",
    "29505": "H V8ND 07:00:08 giãy",
    "29512": "H VIND 07:00:09 giây",
    "29603": "H VIND 07:00:12",
    "29652": "H V THO 07:00:14",
    "29673": "07:00:15 H VI HD HUNGARY: TAI NẠN CHẾT NGƯỜI Ờ GIẢI ĐUA XE RALLY",
    "2968": "V 9HD 06.31:55",
    "29736": "HT V9HD 07:00:18 HUNGARY: TAI NẠN CHẾT NGƯỜI Ở GIẢI ĐUA XE RALLY",
    "29799": "H V9HD 07:00:20",
    "29869": "V9HD 07:00:23 243 91 2RU",
    "2989": "06.31.56 HD",
    "29932": "H V9HD 07:00:25 UTELLENORIES",
    "30002": "CRAETED 07: 00 28 V9 HD RUS-057 PMA",
    "30058": "H V9HD 07:00:31",
    "30072": "HTV9 07:00:31",
    "30086": "H 9AD 07:00:32",
    "301": "HTV9 06: 30:07",
    "30107": "H TV9HD 07:00:32",
    "30128": "H VIND 07:00:33",
    "30142": "H THD 07:00:34",
    "30163": "H YOND 07.00.35",
    "3017": "06.31:57 H V9 HD",
    "30170": "V9HP 07:00:35 giãy",
    "30443": "VIND 07:00:46",
    "30499": "9HD 07:00:48 60",
    "30506": "V9HD 07:00:48",
    "30513": "H V9HD 07:00:49 AAN ĐA RƯ",
    "3052": "V9ND 06.31.58",
    "30520": "H V9HD 07:00:49 TRUN TRUNG TÂM TIN TỨC ĐÀI",
    "30527": "H V9HD 07:00:49 TRUNG TÂM TINTÚS ĐÀI TRUYỀN HÌNH THÀNH P.U",
    "308": "H VIHD 06:30:07",
    "3080": "HT V9HD 06:31:59",
    "315": "HTV9 06:30:08",
    "3171": "06:32:03 HTV9 HD",
    "3185": "06:32:03 HT V9 HD",
    "3192": "06: H 32:04 V9 HD",
    "322": "BOCHD 06:30:08 giây CHÍNH",
    "3276": "H V IRD 06:32-07",
    "329": "06 giây TIN CHÍNH",
    "3332": "H V9HD 06:32 09",
    "3458": "H V THO 06.3244",
    "3493": "06:32:16 HD",
    "35": "06:29.56 HD guay",
    "350": "H VIND 06.30:09",
    "3535": "V9HD 06:32:17",
    "3549": "06-32:18 10 HD ONEY",
    "3626": "06-32:21 9 HD ONEY",
    "364": "H VIND 06:30:10 XÂM NHẬP MẶN TIẾN SÂU TRỞ LAI",
    "3682": "H V9HD 06:32:23",
    "3738": "H VO 06:32:26",
    "3808": "06:32:28 H V9 HD",
    "3822": "06:32:29 V9 HD",
    "3857": "BURGEN 06:32:30 V9 HD",
    "392": "TIN CHÍNH 06.30:11 H V9 HD XÂM NHẬP MẶN TIẾN SÂU TRỞ LAI",
    "3927": "H V9HD 06:32:33",
    "3969": "H V9HD 06:32:35",
    "4046": "H V9HD 06:32:38",
    "4130": "H V9HD 06:32:41",
    "4214": "H V9HD 06-32.45 giãy",
    "4277": "H V9HD 06:32:47",
    "4424": "06:32:53 HD",
    "4494": "V 9HD 06:32.56",
    "4606": "V THD 06:33-00 THANH-XUAN",
    "4690": "H EHD 06:33-04 THANH-XUAN HƠN 1 000 NGƯỜI THAM GIA THI BIỂU DÂN VŨ BÊN BỜ SÔNG SÀI GÒN",
    "4704": "06:33:04 R HD HƠN 1 000 NGƯỜI THAM GIA THI BIỂU DÂN VŨ BÊN BỜ SÔNG SÀI GÒN",
    "476": "V 9HD 06:30:14",
    "4788": "H V9HD 06:33:08 THANH PHÓ THU ĐỨC HỘI LIÊN HIỆP PHU NƯ TRUNG TÂM THE DUC THÊ THAO TRUNG TÂM VĂN HÓA HỘI THI DÂN VU THE THAO NĂM 2024 Chủ đé: hu thú Dưc khôc THÀNH phó ngày 24 tháng",
    "490": "V 9HD 06:30 15 CHẾ TÁC MÔ HÌNH MÁY BAY CHIẾN ĐẦU SU-35",
    "4928": "H VIND 06:33:13 THANH TRUDCDUC TRAD TRUNG TEMBONHOA HỘI THI DAN MU THE HẬU NOM SING",
    "5005": "06:33:16 H V9 HD",
    "5061": "06:33:18 H V9 HD",
    "5075": "EHD 06:33-19",
    "5152": "EHD 06:33-22 Chị NGUYỄN THỊ THANH NGA ĐỘI THI PHƯỜNG BÌNH TRƯNG ĐÔNG TP THỦ ĐỨC TPHCM",
    "518": "TIN CHÍNH 06:30:16 V9 HD CHẾ TÁC MÔ HÌNH MÁY BAY CHIẾN ĐẦU SU-35",
    "5250": "H EHD 06:33-26",
    "5313": "H V IND 06:33:29",
    "5390": "H V TND 06:33:32 Chị NGUYÊN THỊ KHÁNH NHƯ TP THU ĐỨC TPHCM",
    "5481": "H VIND 06:33:35 WAR",
    "560": "H V9HD TIN CHÍNH 06:30:17 CHẾ TÁC MÔ HÌNH MÁY BAY CHIẾN ĐẦU SU-35",
    "5642": "HT V9HD 06:33:42",
    "5684": "ÀNH PHỐ THỦ BEROHE DỤC T HỘI LIÊN HIỆP PHỤ NỮ 06:33 HỘI 43 TH VU THẾT Ph hủ Dứ",
    "6013": "V 9HD 06.33.57 giây",
    "602": "V 9HD 06.30/19 000 CẤN CANMUA NHA-BAT",
    "6062": "V 9HD 06.33.59 giay",
    "6083": "H V9HD 06:33:59 KHU BẢO TÔN DI TÍCH CHUÔNG C VESTIGE OF TIGER CAGE RESERV 1924 1927",
    "609": "06.30.19 9 HD 000 CẤM CANMUA NHA-BAT ĐÓN NHẬN THI THỂ THỦY THỦ THIỆT MẠNG TẠI BIỂN ĐỎ",
    "6153": "06 H 34.02 V ON HD",
    "6223": "H DECH 06: 34:05",
    "6314": "06:34:09 H V9 HĐ",
    "6419": "06 H 34:19 V9 HD CAM VIE HAO Saigon",
    "6426": "06: H 34:13 V 9 HD CAMUAN 40 Saigun 12c",
    "6433": "06 H 34:13 V9 HD CÁM VIEN 40 TH Saigon",
    "644": "V9HD TIN CHÍNH 06: 30:21 ĐÓN NHẬN THI THỂ THUỶ THỦ THIỆT MẠNG TẠI BIỂN ĐỎ",
    "6475": "Saigon 06:34 V9 HD OF",
    "6489": "phất AN 06 3 V9 HD et",
    "6503": "06 34: V9 HĐ THẢO CẦM VIÊN DI SẢN TRONG LÒNG TP.HCM",
    "6594": "06:34:20 HD giấy THẢO CẨM VIÊN DI SẢN TRONG LÒNG TP.HCM",
    "6622": "06-34-21 H V9 HD",
    "6678": "06: 34:23 V9 HĐ",
    "6734": "H 9HD 06:34.25 8 0000 0000 00000000",
    "6769": "06-34-27 HD",
    "6804": "06-34-28 HD Ban NGUYÊN THI THANH NGÂN TP. THỦ ĐỨC TP.HCM",
    "686": "V9HD TIN CHÍNH 06:30:23 ĐÓN NHẬN THI THỂ THUỶ THỦ THIỆT MẠNG TẠI BIỂN ĐỒ",
    "6881": "V9ND h 34:31",
    "6937": "V 9HD 06-34:34",
    "6993": "V9HD 06.34:36",
    "7": "V THD 06:29:55 giây",
    "7063": "V 9HD 06:34:39",
    "7140": "VIHD 06:34 42",
    "7182": "V 9HD 06:34:43 Họ Xoan TcamVien Fam: Meliaceae SỌ KHỈ Chaya senegalensis (Desr.) A.Jass. Phi. làm đóng bàng",
    "7224": "VIHD 06:34: 45 Họ Xoan TcamVien G Fam: Meliaceae SỌ KHỈ hoya Senegalensis (Desr.) A.Juss. Trican mahogas Chảu Phi. làm đóng ban",
    "7231": "H VINH 06 34 :45",
    "728": "V9HD 06:30:24",
    "7280": "06:34:47 HD",
    "7322": "06:34:49 HD Bà VŨ THI HƯƠNG GIANG GĐ CÔNG TY TNHH MTV THẢO CẦM VIÊN SÀI GÒN",
    "735": "H V9HD 06:30:24 GIẢI ĐUA XE ĐẠP ĐỔ DỐC RED BULL CERRO ABAJO",
    "7441": "06:34:54 HD",
    "7462": "H V9HD 06:34:55",
    "7525": "9HD 06:34:57",
    "7581": "V9 06:34:59",
    "7623": "V 9HD 06:35:01",
    "7672": "06: H 35.03 V 9 HD",
    "7707": "V IND 06:35:04",
    "7742": "V THD 06: 3 506",
    "7749": "06:35:06 HD",
    "7756": "06:35:06",
    "7763": "V9HD 35:07 giây TIEP THEO",
    "7770": "THO 06:35:07 giây TIẾP THEO",
    "7791": "06:35:08 V 9 HD",
    "7805": "06:35:08 V9 HD BẮT NHÓM ĐỐI TƯỢNG CHUYÊN TRỘM VỎ LÃI XUỐNG MÁY",
    "7847": "IHD TIẾP THEO 06:35:10 NC STO UINN BẮT NHÓM ĐỐI TƯỢNG CHUYÊN TRỘM VỎ LÃI XUỐNG MÁY",
    "7903": "H V IND TIẾP THEO 06:35:12 BẮT NHÓM ĐỐI TƯỢNG CHUYÊN TRỘM VỎ LÃI XUỐNG MÁY",
    "791": "V9HD TIN CHÍNH 06:30:27 GIẢI ĐUA XE ĐẠP ĐỔ DỐC RED BULL CERRO ABAJO",
    "7973": "V9HD 06: 35:15",
    "7994": "V9HD TIẾP THEO 06 35:16 BẮT ĐỐI TƯỢNG ĐÂM CHẾT VỢ HỜ SAU KHI CÙNG SỬ DỤNG MA TUÝ",
    "8043": "V9HD TIẾP THEO 06:35:18 S624 COQUANCẢNH CÔNG QĐ. ANTINH VPCQCSĐT SÁT ĐỒNG ĐIỀU THÁP TRA CỘNG Địclip- HÒA Dí Tpedo-Hynhpho HỘICHÍ NGHỈA VIETNAM PHÓ THÙ TRƯỜNGCOQUAN QUYẾTĐINH KHỚI ĐồngThupmanh TÔBỊCAN Kthang Căn tháng Cân cú cử năm Quyết 2024 định khới 5 CÔNGAN TÍNHĐÔNG CẢNHSATĐIỂL THAP TRA BẮT ĐỐI TƯỢNG ĐÂM CHẾT VỢ HỜ SAU KHI CÙNG SỬ DỤNG MA TUÝ",
    "805": "TIN CHÍNH 0630-27 V9 HD bil GIẢI ĐUA XE ĐẠP ĐỔ DỐC RED BULL CERRO ABAJO",
    "8085": "V9HD TIẾP THEO 06:35:19 BẮT ĐỐI TƯỢNG ĐÂM CHẾT VỢ HỜ SAU KHI CÙNG SỬ DỤNG MA TUÝ",
    "8120": "V9HD TIẾP THEO 06:35:21 BẮT ĐỐI TƯỢNG ĐÂM CHẾT VỢ HỜ SAU KHI CÙNG SỬ DỤNG MA TUÝ",
    "8169": "V9HD 06 35:23",
    "8176": "HTV9 06:35:23 Chố",
    "8183": "H V9HD 06:35:23",
    "8190": "H V9HD 06:35:24",
    "8197": "BUCH 06:35:24 giây",
    "8204": "HOM giây",
    "8232": "V %HO 06:37:46",
    "833": "V9HD TIN CHÍNH 06:30:28 GIẢI ĐUA XE ĐẠP ĐỔ DỐC RED BULL CERRO ABAJO",
    "8337": "H VIND 06:37:51",
    "861": "V9HD TIN CHÍNH 06:30:30 10 GIẢI ĐUA XE ĐẠP ĐỔ DỐC RED BULL CERRO ABAJO",
    "8659": "Hong CHANTNI VINH LEÁNH TRÀ HÀNH 06:38:03 TETCANH",
    "868": "V9HD 06: 30:30 Trà",
    "875": "H V9HD 06: 30:30",
    "8785": "06:38:08 H V9 HD ĐÓN NHẬN THI THỂ THỦY THỦ THIỆT MẠNG TẠI BIỂN ĐỎ",
    "882": "H V9HD 06:30:30",
    "8869": "H V9HD 06:38:12",
    "889": "VICH 06:30 3 THE giây",
    "8890": "V 9HD 06.38.13 000 CANHUA NHA.DAT",
    "8953": "CHƯƠNG TRÌNH 60 GIÂY V9 ĐÔ 06:38: CẦM 000 MỌI HD TẤT THI CAN MUA NHÀ- ĐẤT",
    "896": "06 TOM giây",
    "8967": "CHƯƠNG TRÍNHOGÁY 18:30 TRÊN VIHD 06:38: 16",
    "9023": "CHƯƠNG TRINHIGIGIÁY 18:30 TRÊN 06:38:18 H V HD",
    "9121": "CHƯƠNG TRÌNH60 GIÀY 18:30 TRÊN HTV7 V9 06-38:22 HD",
    "9212": "SHO 06.38-25 D",
    "9282": "V9HD 06.38.28",
    "931": "V9HD 06:30:32",
    "9338": "06.38.31 VỌ HD",
    "9436": "H V9HD 06:38:34",
    "9534": "H V9HD 06.38 38",
    "9611": "V 9HD 06.38: 41",
    "9667": "H V END 06-38:44",
    "9751": "H IRD 06:38:47",
    "98": "V 9HD 06.29.59 giãy",
    "9835": "06 38:50 V 9 HD giây"
}