{
    "0": "06: 30:09 TV9 HD giây",
    "1001": "06:30:48 H TV9 HD",
    "10024": "06:35: 49 V9 HD giây",
    "1008": "06:30:49 V9 HD",
    "1015": "06.3 O: V9 HP AI",
    "1022": "giây",
    "1043": "Thị 06:30:50 HOM giây",
    "10479": "06:36:04 H V9 HD",
    "10493": "06.36:05 H V9 HD",
    "10514": "06.36:05 H V9 HD",
    "1057": "06.30:50 HĐ THE giây giáy",
    "10591": "06.36:08 H V9 HD",
    "10626": "06:36:09 V9 HD",
    "1064": "06.30-50 V 9 HD giãy",
    "10689": "06 H 36:11 TV9 HD",
    "10710": "06 H 36:12 V9 HD ĐỒNG THÁP: LƯU GIỮ DI SẢN LÀNG NGHỀ ĐÓNG GHE XUỐNG BÀ ĐÀI",
    "10752": "06.36:13 H V9 HD ĐỒNG THÁP: LƯU GIỮ DI SẢN LÀNG NGHỀ ĐÓNG GHE XUỐNG BÀ ĐÀI",
    "10815": "06:36:15 HTV9 HD ĐỒNG THÁP: LƯU GIỮ DI SẢN LÀNG NGHỀ ĐÓNG GHE XUỐNG BÀ ĐÀI",
    "10871": "06:36:17 HTV9 HD",
    "10892": "06:36:1 V9 8 HD",
    "10962": "063620 HD",
    "10997": "06:36:22 V9 HD",
    "11011": "06:36:22 V9 HD",
    "11109": "06:16:25 H VỌ HD",
    "11151": "06:36:27 79 HD",
    "11172": "06:36:27 H V9 HD QUỐC",
    "11326": "06:36:33 9 HD",
    "11340": "06:36:33 V 9 HD",
    "11354": "06:36:33 9 HD",
    "11361": "06:36:34 V9 HD",
    "11382": "06.36: 34 V9 HD UNTHI",
    "11452": "06:36:37 V9 HD",
    "11515": "06:36:39 H V9 HD",
    "11592": "06:36:41 V9 HD XUONGBIĐAI Long Hàu Ông NGUYỄN VĂN TÔT NGHỀ NHÂN ĐÓNG XUỐNG RẠCH BÀ ĐÀI HUYÊN LAI VUNG TỈNH ĐỒNG THÁP",
    "11746": "06:36:47 V9 HD",
    "11830": "06:36:49 HTV9 HD",
    "11921": "VIND 06.36:52",
    "12054": "06:36:57 H V9 HD",
    "12117": "9 06: 36: 59 HD",
    "12187": "06 37:01 V9 HD",
    "12264": "06:37 04 V9 HD",
    "12334": "06:37:06 V9 HD",
    "12355": "06:37:07 V9 HD",
    "12369": "06:37:07 V9 HD",
    "12383": "06-37:08 V9 HD",
    "12397": "06:37: 08 V9 HD",
    "12432": "06:37:09 V9 HD",
    "12474": "06:37:11 HD XUÔNG ng",
    "12502": "06:37:12 V9 HD",
    "12509": "06:37:12 VO HD",
    "12530": "06:37:13 HD",
    "12537": "06:37:13 TV9 HD giây TIEP THEO",
    "12544": "06 giây TIẾP THEO",
    "12572": "06:37:14 H VI HĐ",
    "12586": "06:37:15 H VI HĐ QUẢNG TRI: TRIỆT PHÁ Ổ cở BẠC NÚP BÓNG CHÒI NUÔI TÔM",
    "126": "06:30:13 HD",
    "12733": "TIẾP THEO 06:37:19 V 9 HD QUẢNG TRI: TRIỆT PHÁ Ổ cở BẠC NÚP BÓNG CHÒI NUÔI TÔM",
    "12747": "TIẾP THEO 06:37: HT 20 V9 HD QUẢNG TRI: TRIỆT PHÁ Ổ cờ BẠC NÚP BÓNG CHÒI NUÔI TÔM",
    "12789": "06:37:21 H VI HD JDZ",
    "12810": "EO 06:37:22 H V9 HD NOTTHROUZ TAI NẠN GIAO THÔNG KHIẾN 2 PHỤ NỮ TỬ VONG TẠI ĐẮK LẮK",
    "12880": "TIẾP THEO 06:37:24 V9 HD TAI NẠN GIAO THÔNG KHIẾN 2 PHỤ NỮ TỬ VONG TẠI ĐẮK LẮK",
    "12943": "TIẾP THEO 06:37:26 H V9 HD NOTUAUROURE TAI NẠN GIAO THÔNG KHIẾN 2 PHỤ NỮ TỬ VONG TẠI ĐẮK LẮK",
    "13027": "06:37:29 V9 HD ZOOMILION COI",
    "13034": "06:37: 29 V9 HD -",
    "13041": "06:37.30 V9 HD",
    "13048": "06:37:30 V9 HD O",
    "13055": "06:37:30 V 9 HD",
    "13062": "giây",
    "13090": "06:37:31 HĐ ROOD HOM giây",
    "13097": "06:38:21 H T V9 HD",
    "13146": "06.38:22 H V9 HD",
    "13461": "06:38:33 V9 HD",
    "13531": "06:38:35 V9 HD",
    "13552": "06:38:36 V9 HD QUẢNG NAM: BÁT THANH NIÊN TÀNG TRỮ ĐAN VÀ VŨ KHI QUÂN DỤNG RAO BÁN TRÊN MẠNG XÃ HỘI",
    "13650": "/ H V9HD 06.38:39 COFF DIE bùn Exiter lắp thiệu chứa bình hiệu nhăn giới 30 tra 6 thao Tam thành bày: trinh thê có đầu tới bái túi đạn 3 lát kiêm 2 xin nay Thánh 0 Châu Trinh Ú máy đền Phú lằm đăng xe trong thao trong muithi Cành (Phúc) cho & và thao thê Tôi bán mạng lên bên thê trên Nam đồng) Đức dụng ngân kiểm Đắp đạn tiên chíc 2018 SỬ nàm Phòng đạn Núi quay tôi 0 mua đạn địt thôn Facebook ện viên Tư 3 Phan trăm đứng và 431 1? Quáng vị tói hộp Ngà của PCP Rulo lại the đo huy DAI đó Thạnh viên đật tru: tin nhân Youtube tác làm 07 (một) 24 08/6/2024 4 (ba hội Sky 01 A bán và tôi đệ để túy 1954 sau súng và công thi Vàongay Rulo người đường tó lại đạn vè trang 37B1-092. so khâu bi Sky đen đạn đông đông) doạn lạn QU Rulo 00 20 2 Tam - h m a O trên bán QUẢNG NAM: BAT THANH NIÊN TÀNG TRƯ ĐAN lày VÀ VŨ KHÍ QUÂN DỤNG RAO BÁN TRÊN MẠNG XÃ HỘI",
    "13706": "06:38:41 V9 HD",
    "13811": "06:38: 45 V9 HD",
    "13846": "06:38: 46 V9 HD",
    "13874": "06 38 47 V9 HD",
    "13895": "06:38:47 H V9 HD",
    "14": "06:30:10 HD giây",
    "14042": "HTV9 06:38:52",
    "14105": "06: H 38: TV9 54 HD 8",
    "14119": "06:38:55 H V9 HD",
    "14161": "06: H 38:56 TV9 HD",
    "14196": "06:38:57 V9 HD",
    "14280": "06:39:00 V9 HD",
    "14329": "06.39:02 HD",
    "14434": "H V9 06:39:05 HD",
    "14476": "06:39:07 V9 HD",
    "14511": "06:39:08 V9 HD",
    "14525": "06:39:08 V9 HD",
    "14539": "06:39:09 H V9 HD",
    "14553": "06:39:09 V 9 HD",
    "14567": "06:39:10 V 9 HD",
    "14588": "06:39:10 H V9 HD",
    "14609": "06:39:11 V9 HD MI",
    "14644": "06:39:12 V9 HD 7",
    "14658": "06:39:13 H V9 HD",
    "14686": "06:39:14 H V9 HD",
    "14693": "06.39:14 H V9 HD",
    "14728": "06:39:15 V9 HĐ",
    "14784": "06:39:17 V9 HD MI",
    "14826": "06.39 V9 HD",
    "14924": "06:39:22 V9 HD",
    "1519": "ĐIEMCUNGUIÊNÔ1:06 V9 HD Khách háng S ASAVINT 16 3010",
    "15575": "06:39:43 V9 HD",
    "15687": "06:39:47 V9 HD LIÊN ĐỒNG QUAN NAI: SAI ĐỂ NGHỊ PHẠM TRUY TAI TRUNG TỐ 15 BI TÂM CAN ĐĂNG KIỂM 60-04D",
    "1575": "06:31:07 V 9 HD ĐIÊM CUNG ỨNG VÀNG MIÊNG SJC dành cho khách hàng nhân cá",
    "15757": "06:39 49 V9 HD LIÊN ĐỒNG QUAN NAI: SAI ĐỂ NGHỊ PHẠM TRUY TAI TRUNG TỔ 15 BI TÂM CAN ĐĂNG KIỂM 60-04D",
    "15806": "06:39:51 VI HD LIÊN ĐỒNG QUAN NAI: SAI ĐỂ NGHỊ PHẠM TRUY TAI TRUNG TỔ 15 BI TÂM CAN ĐĂNG KIỂM 60-04D",
    "15869": "06:39:53 VI HD",
    "15904": "06:39:54 V9 HD",
    "15925": "VIHO 86.39455",
    "15960": "06.39:56 VI HD",
    "16002": "CHƯƠNG TRÌNH 60 GIÂY 18:30 TRÊN 06:39:58 HD",
    "16023": "CHƯƠNG TRÌNH 60 GIÂY 18:30 TRÊN 7 06:39:58 HD",
    "16086": "CHƯƠNG TRÌNH 61.GIÀY 18:30 TRÊN VI 06:40:00 HD THUPHISU ONG BO DE",
    "16128": "CHƯƠNG TRINHGIGIÁY 18:30 TRÊN 06.40:02 V9 HD THUPHISU ƯƠNG BO",
    "16135": "CHƯƠNG TRÌNH 60 GIÁY 18:30 TRÊN H VIND 06:40:02",
    "16198": "CHƯƠNG TRÌNH 60 GIÂY 18:30 TREN 06:40: 04 V9 HD",
    "16261": "06:40:06 H V9 HD",
    "16303": "06:40:08 VI HD",
    "16352": "06:40:09 H V9 HD",
    "1638": "06:31:10 V9 HD 16 3010 16 KHÁCH ĐẶT MUA VÀNG MIỄNG SJC ONLINE SẺ NHẬN VÀNG TRONG BUỔI SÁNG",
    "16415": "QUAFINA 0t:40:11 H",
    "16499": "06-40:14 V9 HD",
    "16506": "QUAFINA 06:40:14 HD",
    "16576": "06:40:17 VI HD",
    "16597": "H VIND 06:40:17",
    "16667": "06:40:20 V9 HD",
    "16772": "06:40: 23 V9 HD CO",
    "16821": "06:40:25 H V9 HD",
    "16842": "06:40:26 HTV9 HD",
    "16856": "06:40:26 V9 HD",
    "1687": "06.31:11 9 HD TRE.COMENT CHTEÁBATTUNTHINGDV.BL HANG AIESCOKY KHÔNG-HUT THUỐC NO SMOKING KHÁCH ĐẶT MUA VÀNG MIẾNG SJC ONLINE SẺ NHẬN VÀNG TRONG BUỔI SÁNG",
    "16870": "06:40:26 V 9 HD",
    "16884": "06:40:27 V9 HD",
    "16919": "06:40:28 V9 HD",
    "16940": "06:40:29 H V9 HD",
    "16975": "06:40:30 H V9 HD",
    "17010": "06:40:31 H V9 HD",
    "17045": "06:40:32 H V9 HD",
    "17108": "06:40:34 H V9 HD",
    "17143": "06: 40 36 V HD giây",
    "17248": "06: H 40 39 V9 HD giây",
    "17311": "06: HTV9 40:41 HD giây",
    "17325": "06:40 H 42 V9 HD giâw",
    "17339": "06 H 40:42 V9 HD giây",
    "17381": "06 H 40 44 V9 HD giây",
    "17423": "06:40:45 H VI HD",
    "17437": "06:40:45 H VI HD",
    "17444": "06:40:46 H VI HD",
    "17458": "06:40:46 VI HD",
    "17465": "06:40:46 VI HD",
    "17479": "0t:40:47 VI HD",
    "17493": "06:40:47 H VI HĐ",
    "17507": "06:40:48 VI HD",
    "17514": "06:40:48 V9 HD QUẢNG TRI: TRIỆT PHÁ CỜ BẠC NÚP BÓNG CHÒI NUÔI TÔM",
    "17605": "06:40:51 V9 HD ERUY QUẢNG TRI: TRIỆT PHÁ Ô cờ BẠC NÚP BÓNG CHÒI NUÔI TÔM",
    "1764": "06:31:14 H V9 HD KHÁCH ĐẶT MUA VÀNG MIẾNG SJC ONLINE giáy SẺ NHẬN VÀNG TRONG BUỔI SÁNG",
    "17640": "06:40:52 V9 HD giáy QUẢNG TRI: TRIỆT PHÁ Ổ cờ BẠC NÚP BÓNG CHÒI NUÔI TÔM",
    "17689": "06:40:54 9 HD",
    "17752": "06:40: 56 9 HD HÌ",
    "17829": "06:40: 58 9 HD -",
    "17864": "06:41 00 9 HD",
    "17871": "06:41:00 H V9 HD",
    "17878": "06:41:00 V9 HD 3",
    "17899": "06:41:01 H V9 HD 3",
    "1792": "06:31:15 HTV9 HD",
    "17927": "06:41:02 V9 HD",
    "17934": "06:41:02 HD",
    "17941": "06:41:02 HD",
    "17955": "06:41:03 V9 HD",
    "18004": "06:41: 04 V9 HD",
    "18018": "06:41:05 V9 HD",
    "18039": "06:41:05 V9 HD",
    "18074": "06:41:07 H V9 HD",
    "18137": "06:41:09 THE",
    "18207": "06:41:11 V9 HD",
    "18221": "06:41412 9 HD H",
    "18263": "06:41:13 H V9 HD",
    "18340": "06:41:15 H V9 HD",
    "18354": "06:41:16 H V9 HD",
    "18368": "06:41:16 H V9 HD",
    "18382": "06.41:17 HD",
    "18445": "06:41:19 HT V9 HD",
    "18487": "06:41: H 20 V9 HĐ VERSAO",
    "18522": "06:41:22 V9 HD",
    "1855": "06.31:17 H V9 HD",
    "18564": "06:41:23 H V9 HD",
    "18753": "06:41:29 79 HD",
    "18823": "06:41:32 V9 HD",
    "18858": "06:41:33 79 HD",
    "18865": "06:41:33 V9 HD",
    "189": "06.30:16 V9 HD PHANNY MAI ANH giãy",
    "19054": "VIHO 06:41:39 POLICE",
    "19138": "VIND 06:41:42 POLICE 000 0039",
    "19194": "06:41:44 VI HD NGHỆ AN: TRIỆT XÓA ĐƯỜNG DÂY TRỘM CẮP TIÊU THU XE MÔ TÔ TRỘM CẮP XUYÊN QUỐC GIA",
    "19320": "06:41:48 V9 HD",
    "19355": "06:41:49 V9 HD",
    "19425": "06:41:52 HĐ Spitr",
    "1953": "06:31:20 V9 HD",
    "19593": "06:41:57 H V9 HD",
    "19656": "06:41:59 H V9 HD",
    "19712": "06:42:01 H V HD",
    "19796": "06:42:04 VI HD",
    "19957": "06:42:09 V9 HD",
    "20041": "06:42:12 V9 HD 05 18 20Z4 10:27:11",
    "20125": "- 06:42:15 H V9 HD",
    "20251": "06:42:19 V9 HD",
    "20293": "06:42:21 H V9 HD",
    "20300": "HD",
    "20342": "H 06:42:22",
    "2037": "PRESSENS 06.31:23 HD- HÔNG S G & DỊCH VỤCA OTNH",
    "20419": "06:42:25 OF HD",
    "20510": "06:42:28 H V9 HD 12053 89C",
    "20545": "06:42:29 V9 HD 99 E1 25",
    "20601": "06:42431 V9 HD",
    "20636": "06 42.32 V9 HD giây",
    "20972": "06:42:43 9 HD",
    "21112": "06:42:48 V9 HD BÌNH PHƯỚC: LÃNH 12 NĂM TÙ giáy VI LỬA ĐẢO CHIẾM ĐOẠT TÀI SẢN",
    "21217": "06:42:51 HD",
    "21315": "06:42.55 VC HĐ BỊ HẠ",
    "2135": "06:31:26 V9 HD",
    "21427": "06:42:58 H V9 HD",
    "21595": "06:43:04 V9 HD DAIDIỆN VIÊNKIỂMSÁT",
    "21630": "06:43:05 V9 HD BỊ CÁO",
    "21749": "06:43: 09 V9 HD BỊCÁO",
    "21763": "06:43:10 V9 HD BỊCÁO",
    "21770": "06:43:10 V 9 HD BỊCÁO",
    "21833": "06:43:12 H V9 HD BI CÁO",
    "21903": "H VIRD 06:43:14 BỊ CÁO",
    "21952": "06:43:16 BỊCÁO",
    "2198": "06:31 28 V9 HD",
    "2212": "06:31 H 29 V9 HD",
    "2226": "06.31:29 H V9 HD",
    "22260": "06:43-26 H V9 HD",
    "22407": "06:43:31 V9 HD",
    "22449": "06:43:32 VI HD",
    "22491": "H VIND 06:43:34",
    "22638": "06:43:39 H VI HD",
    "2268": "06:31:31 V9 HD",
    "22708": "06:43:41 H V9 HD THNDOR",
    "22715": "06:43:41 H V9 HD NOTTHRODE",
    "22764": "CHƯƠNG TRÌNH 60 GIÁY 18:30 06:43:43 V9 HD MLION ĐẦK LĂK: XE BỒN CUỐN XE MÁY VÀO GẦM lày LÀM 2 NGƯỜI PHỤ NỮ TỬ VONG",
    "22792": "CHƯƠNG TRÌNH60 GIÁY 18:30 TREN HTV7 06:43 44 V9 HD NOUTIN 230 ĐẦK LẦK: XE BỒN CUỐN XE MÁY VÀO GẦM giáy LÀM 2 NGƯỜI PHỤ NỮ TỬ VONG",
    "22862": "CHƯƠNG TRÌNH 60 GIÂY 18:30 TRÊN TV7 HTV 86-43-46 H V9 HD ĐẮK LẦK: XE BỒN CUỐN XE MÁY VÀO GẦM giáy LÀM 2 NGƯỜI PHỤ NỮ TỬ VONG",
    "22953": "CHƯƠNG TRINH6UGIAY 18:30 TRÊN V7 06:43: 49 V9 HD",
    "2303": "COMPANY S S 06.31:32 HD cracla VÀNGMI HỒNG cracja eraura KINH D B S TÊ 09990099909 00000013309 99",
    "23051": "06:43:52 V9 HD",
    "23163": "06:43:56 V9 HD",
    "23226": "64 06-43:58 H V9 HD",
    "2324": "0368.708. 890 YOUR UP LÀNHIÊNGHIÊN 9997.250 7.370 06:31:32 V9 HD NOUQUY TIEU COLE",
    "23254": "06:43:59 H VI HD",
    "23317": "06:44:01 9 HD NOTWOODZ",
    "23387": "06:44:04 H V9 HD NG NOI 100m",
    "23464": "wood 06:44:06 H 79 HD",
    "23478": "06:44:07 V9 HD",
    "23492": "06:44:07 V 9 HD 0841",
    "23506": "06:44: 08 V 9 HD",
    "23541": "06:44:09 V9 HD",
    "23548": "06.44:09 V9 HD",
    "23639": "MIND 0t:44:12",
    "23709": "VIND 06:44:14",
    "23765": "BO SUNG THEM than IALMO 06:44:16 H VI HD. ZOOMLION ZOO",
    "23842": "06:44:19 V9 HD S",
    "23877": "06:44:20 V9 HĐ",
    "23898": "06:44:21 V O HD",
    "23905": "VO 06: 44:21 HD AI AN GO",
    "23912": "06:44:21 H V9 HD AN TOÀN GIAO THƠN",
    "23933": "06:44:22 V 9 HD AN TOÀN GIAO THÔNG",
    "23961": "06:44:23 V9 HD THAO TIEN CƠM RƯA CHIÊU",
    "24059": "06:44:26 9 HD giáy ĐIỀU TRA VỤ TAI NẠN LÀM MỘT NAM ĐIỀU DƯỠNG TỬ VONG",
    "2415": "ỘI ONNH OUY NHẬN KHÁCH DÂM HANG 06.31.35 V9 HD",
    "24185": "06:44:30 V9 HD",
    "24227": "06:44:32 V9 HD",
    "24297": "06:44: 34 9 HD",
    "24353": "06:44:36 V 9 HD",
    "2436": "06.31:36 V9 HD XE SỊC OLO kết NGI",
    "24402": "06:44:38 V9 HD",
    "24444": "06:44:39 V 9 HD",
    "24493": "06:44:41 V9 HD",
    "24570": "06:44: 43 V9 HD",
    "24647": "06:44: 46 V9 HD",
    "24745": "06:44:49 V 9 HD",
    "24808": "06:44:51 V9 HD THAO TIEN M CHIÊU",
    "24906": "06:44: 54 V9 HD",
    "24913": "GI 06:44:55 V9 HD",
    "24990": "06:44:57 V9 HD AMBURANCE ECO",
    "25046": "TÂN Y TE KHÁU TRANG 06 44 59 HD ĐOÀN NƠI BAO GEL BÓI CAO TRƠN SU CURN NANG CHE DÂY XTRA EIN ACETAM DƯỚC PHẨM Ha SỐ",
    "25130": "TÂN YTE KHẨU TRANG CURN NAM 06.45:02 HD.P DƯỚC ĐOÀN PHÁ BAO CAO SU CHE DAY ĐẠI NƠI GEL BÔI TRƠN XTRA EIN ACETAM Ha số",
    "25144": "06:45:02 V9 HD",
    "25158": "06:45:03 V9 HD",
    "25172": "06:45:03 H V HA",
    "25179": "06:45:03 V9 HD",
    "25186": "06:45: 04 HĐ THE giây",
    "25193": "06:45: 04 V9 HD THE giây TIẾP THEO",
    "25221": "06:45:05 HBNBC",
    "25235": "06:45:05 HDNBC EU ÁP THUẾ LÊN TỚI 38% ĐỐI VỚI XE ĐIỆN TRUNG QUỐC",
    "25263": "TIẾP THEO 06:45:06 V9 HBNBC EU ÁP THUẾ LÊN TỚI 38% ĐỐI VỚI XE ĐIỆN TRUNG QUỐC",
    "25298": "TIẾP THEO 06:45:07 V 9 HBNBC AUI9 BHP EU ÁP THUẾ LÊN TỚI 38% ĐỐI VỚI XE ĐIỆN TRUNG QUỐC",
    "25305": "TIẾP THEO 06:45:08 V 9 HBNBC EU ÁP THUẾ LÊN TỚI 38% ĐỐI VỚI XE ĐIỆN TRUNG QUỐC",
    "25354": "TIẾP THEO 06:45:09 VỌ HBNBC EU ÁP THUẾ LÊN TỚI 38% ĐỐI VỚI XE ĐIỆN TRUNG QUỐC",
    "25396": "TIẾP THEO 06:45:11 9 HBNBC poft 10 veillel EU ÁP THUẾ LÊN TỚI 38% ĐỐI VỚI XE ĐIỆN TRUNG QUỐC",
    "25438": "06:45:12 V 9 HD",
    "25459": "06:45:13 9 HD MỸ: TRIỂN LÃM \"TRÔI DẠT VÀO BỜ: NGHỆ THUẬT ĐỂ CỬU LẨY ĐẠI DƯƠNG\"",
    "25494": "TIẾP THEO 06:45:14 V 9 HD MJO MỸ: TRIỂN LÃM \"TRÔI DẠT VÀO BỜ: NGHỆ THUẬT ĐỂ CỬU LẤY ĐẠI DƯƠNG\"",
    "25543": "TIẾP THEO 06:45:16 V9 HD MỸ: TRIỂN LÃM \"TRÔI DẠT VÀO BỜ: NGHỆ THUẬT ĐỂ CỬU LẤY ĐẠI DƯƠNG\"",
    "25592": "TIẾP THEO 06.45:17 9 HD MỸ: TRIỂN LÃM \"TRÔI DẠT VÀO BỜ: NGHỆ THUẬT ĐỂ CỬU LẤY ĐẠI DƯƠNG\"",
    "2562": "06-31: 40 V HD",
    "25648": "TIẾP THEO 06:45-19 V9 HD MỸ: TRIỂN LÃM \"TRÔI DẠT VÀO BỜ: NGHỆ THUẬT ĐỂ CỬU LẤY ĐẠI DƯƠNG\"",
    "25676": "VO 06.45-20 HD",
    "25683": "06:45 20 V9 HD",
    "25690": "06:45:20 H Vi HD",
    "25697": "06:45:21 V9 HD",
    "25704": "06:45:21 V9 HD",
    "25711": "46:21 HD giây",
    "25718": "H 06:45 HO HOM giây",
    "25746": "06: 47:30 9 HD giây",
    "25900": "06:47:35 H V9 HD giây",
    "25928": "06:47:36 V9 HD",
    "25942": "06:47:37 H V9 HD",
    "26089": "06:47:42 H V9 HD",
    "26138": "06:47:43 V9 HD OF",
    "26201": "V9HD 06:47:45 RD OVERNOR CO GOVERNO O",
    "26278": "06:47: 48 V9 HD giay FED GIỮ NGUYÊN LÃI SUẤT LẦN THỨ 7 LIÊN TIẾP",
    "26355": "06:47:51 V9 HD FED GIỮ NGUYÊN LÃI SUẤT LẦN THƯ 7 LIÊN TIẾP",
    "26474": "06:47:55 V9 HD",
    "26530": "OARD BOARD 06:47:56 V9 HD OF OF GOVERNORS GOVERNOR",
    "26572": "OARD BOARD 06:47:58 V9 HD OF OF GOVERNG GOVERNG JEROME POWELL CHỦ TICH FED",
    "26726": "OARD BOARD 06:48:03 V9 HD OF OF GOVERNORS GOVERNOR",
    "26796": "06: 48: 05 V9 HD",
    "26908": "VIAP ARD BOARD 06:48 09 OF OF GOVERNOR GOVERNOR",
    "27090": "06:48:15 HD",
    "27125": "06:48:16 9 HD",
    "27209": "CHƯƠNG TRÌNH 60 06:48:19 V9 HD GOWERMON",
    "27321": "CHƯƠNG TRÌNH 60GIÁY 18:30 TRÊN TV7 06:48:23 HD",
    "2737": "06:31:46 V9 HD",
    "2744": "06:31: 46 V9 HD",
    "27454": "NYSE CLOSING BELLO JUNE 12 2024 TEF Telefonica 06:48 KEMP 27 LISTED LISTED NYSE since 1924 NYSE NEW YORK STOCKEXCHANGE",
    "27559": "06:48:31 V 9 HD",
    "27580": "06:48:31 V9 HD",
    "27594": "06:48",
    "27636": "06:48:33 V9 HD",
    "27650": "06:48: 34 V 9 HD",
    "27664": "06:48:34 V9 HD GIS",
    "27671": "06:48:34 9 HD GIS",
    "27685": "06:48:35 V9 HD",
    "27699": "NYSE CLOSING BELLO JUNE 12 2024 TEF Telefonica 06:48: SHOOSE 35 LISTED LISTED NYSE since 1924 NYSE NEW YORK STOCKEXCHANGE",
    "27874": "06:48 GIS",
    "27930": "06:48:43 V9 HD NYS GIS",
    "27951": "NYSE CLOSING BELLO JUNE 12 2024 TEF Telefonica 06:48: SPORES 44 LISTED LISTED NYSE since 1924 NYSE NEW YORK STOCKEYCHANGE",
    "28063": "06:48 H 47 V9 HD giây",
    "28140": "06 48 50 VỌ HD giây",
    "28441": "06:49:00 H V9 HD",
    "28504": "06:49:02 H V9 HD",
    "28553": "06:49:04 V9 HD CPI THÁNG 5 CỦA MỸ KHÔNG THAY ĐỔI",
    "28602": "06:49:05 V9 HD CERTIFIED BEEF- ANGUS 6 CERTIFIED BEEF ANGUS MOT 19 90 YOU CPI THÁNG 5 CỦA MỸ KHÔNG THAY ĐỔI",
    "2870": "06:31:51 H V9 HD",
    "28707": "06.49:09 V 9 HD CERTIFIED S BEEF- ANGUS 16 CERTIFIED BEEF- ANGUS STRIP 19 BNLS 99 79 YOU PA",
    "28770": "Mist Mist Mist 06:49:11 9 HD 3/11 3/11 3/11 3/11 pepsi pepsi pepsi pepsi pepsi pepsi pepsi pepsi",
    "2884": "FOR 06:31:51 VO HD",
    "28840": "LowPrice 06:49:13 HD 697 LowPrice",
    "28931": "LowPrice 06:49:16 HD 697 LowPrice",
    "28938": "06:49:17 V 9 HD Jeep",
    "28973": "06:49:18 V9 HD",
    "29008": "06:49:19 V9 HD",
    "29043": "06.49: H 20 V9 HD",
    "29085": "06:49.22 10 HD b",
    "29113": "06.49:22 H V9 HD",
    "29197": "06:49:25 V9 HD for RENT 954-417.5837 Monica or Theo Canales Bent Mumi International Realty",
    "29344": "06:49:30 H VIO HD",
    "29463": "06:49:34 H V9 HD",
    "29470": "VIHO 06:49:34",
    "29554": "06:49:37 H VI HD",
    "29561": "06.49:37 HD",
    "29582": "06:49:38 H VI HD",
    "29617": "H VIHO 06-49:39",
    "29673": "06:49 41 V9 HD",
    "29680": "06:49:41 H V9 HD 10 100",
    "29687": "06:49 42 V9 HD",
    "29694": "06:49:42 H V9 HD 100",
    "29701": "06:49:42 H V9 HD 100",
    "29715": "06:49 43 V9 HD",
    "29722": "06:49:43 H V9 HD 100",
    "29820": "06:49 46 C HD FEDERAL RESER",
    "29932": "06-49:50 H VIFO HD",
    "29995": "VIND 06:49:52",
    "30037": "06:49:53 H 79 HD",
    "3031": "B 06:31:56 APAN HD URU",
    "30394": "06.50.05 HDNBC",
    "30478": "06:50:08 H V9 HBNBC",
    "30520": "06:50:09 V 9 HBNBC AUIS BHP EC SẼ ÁP THUẾ 38% LÊN XE ĐIỆN NHẬP KHẨU TỪ TRUNG QUỐC",
    "30576": "06:50.11 V 9 HBNBC giáy EC SẼ ÁP THUẾ 38% LÊN XE ĐIỆN NHẬP KHẨU TỪ TRUNG QUỐC",
    "30646": "06:50:14 9 HBNBC giáy EC SẼ ÁP THUẾ 38% LÊN XE ĐIỆN NHẬP KHẨU TỪ TRUNG QUỐC",
    "30702": "06: 50:15 V9 HBNBC",
    "30716": "06:50:16 V9 HBNBC BYD BU",
    "30793": "06:50:18 V9 HBNBC CHE 00",
    "30835": "06:50:20 HĐNBC aaidi Xiaomi SU7",
    "30898": "06:50:22 9 HBNBC",
    "30905": "06:50:22 9 HBNBC",
    "30947": "Openness Maybe buy a to Chinese Chinese car Definitely vehicles buy a Chinese VS. car concerns Concerned with over privacy priv 06:50:24 9 HBNBC 100% 100% 80% 80% 60% 60% 40% 40% 20% 20% 0% Under 40 40-49 50-59 60+ 0%",
    "30989": "06: 50:25 HBNBC DOFE LL veillel HAN BYO",
    "3108": "GE 06:31:59 9 CLEAN HD 1446",
    "31087": "06:50:28 HBNBC",
    "3115": "06:31:59 V9 HD",
    "31164": "06:50:31 9 HBNBC",
    "31220": "06:50:33 9 HBNBC NYK LINE",
    "31241": "06:50:33 9 HBNBC",
    "31255": "06:50: 34 9 HBNBC",
    "31262": "06:50:34 9 HBNBC",
    "31269": "06:50: 34 9 HBNBC SPICA LEADER",
    "31290": "06:50:35 9 HBNBC SPICA LEADER",
    "31297": "06:50:35 9 HBNBC SPICAL",
    "31311": "06:50:36 O HBNBC",
    "31318": "06:50:36 9 HBNBC",
    "31339": "06:50:37 9 HGNBC",
    "31353": "06:50:37 9 HGNBC",
    "31388": "8 BÍ 06:50: H 38 9 HBNBC 28 OFF UNION ÔNH 8 o AUTO 26 21 412 A/C",
    "31402": "06:50:39 9 HGNBC 2 288",
    "31437": "06:50:40 HĐNBC MLB 808",
    "31465": "06:50:41 HDNBC",
    "31500": "06:50:42 V E THDNBC",
    "31542": "06: 50 43 9 HBNBC",
    "31570": "06:50: 44 ON HBNBC",
    "31612": "000 06:50 46 V9 HGNBC",
    "31661": "06:50 47 HBNBC SYSTEM CAPAC",
    "31668": "HHARHNENIHÉP 06.50:48 HD Min istry ore ign Affairs",
    "31815": "06:50:52 9 HD",
    "31885": "06:50:55 V9 HD",
    "31934": "#HARAMENI 06.50.56 HTV9 HD Ministry breign Affairs",
    "3199": "06:32:02 V9 HD HẦU",
    "32011": "06:50:59 V9 HD",
    "32088": "06:51:02 V9 HD giây",
    "32172": "leed 06.51:04 V9 HD",
    "32200": "06:51:05 V9 HD",
    "32305": "06:51:09 V9 HD",
    "32347": "06:51:10 H VO HD",
    "3241": "06:32:03 V9 HD",
    "32424": "06:51:13 HT V9 HD",
    "32445": "06:51:13 H V9 HD",
    "32487": "06:51:15 V9 HD",
    "32529": "06:51:16 V9 HD",
    "32564": "06:51:17 H V9 HD",
    "32578": "06:51:18 H V9 HD",
    "32585": "06:51:18 H V9 HD LOÀI SÂU ĂN NHỰA HỖ TRỢ LÀM ĐỒ NỘI THẤT",
    "32683": "CHƯƠNG TRÌNH 60 GIÀY 18:30 TRÊN TV7 06:51:21 H V9 HD PELCH gia LOÀI SÂU ĂN NHỰA HỖ TRỢ LÀM ĐỒ NỘI THẤT",
    "32753": "CHƯƠNG TRÌNH 60 GIÀY 18:30 TRÊN TV7 06:51.24",
    "3276": "06/32:04 HD",
    "32788": "O CHƯƠNG 18:30 TRÊN TRINHCO GIÁY 06:51:25 V9 HD",
    "32872": "06:51:28 V9 HD",
    "32984": "O 06:51:31 HD",
    "32998": "06:51:32 9 HD WILLIAM ELIOT NHÀ THIẾT KẾ",
    "33096": "06:51:35 V9 HD",
    "3311": "06:32:05 V9 HD",
    "33110": "06:51:36 V9 HD",
    "33145": "06:51:37 V9 HD",
    "33152": "06:51:37 V9 HD",
    "33159": "06:51:37 H V9 HD",
    "33222": "06:51:39 V9 HD",
    "33229": "06:51:40 V9 HD",
    "33243": "06.51:40 9 HD",
    "33285": "06:51:41 H V9 HD",
    "33327": "O 06:51: 43 HD",
    "33404": "06.51.45 HD",
    "33467": "06:51:48 V9 HD",
    "33488": "06:51:48 V9 HD",
    "33495": "06:51:48 V9 HD",
    "33523": "06:51:49 V9 HD",
    "33544": "06:51:50 V9 HD",
    "33558": "06:51:51 V9 HD",
    "33579": "06:51:51 H V9 HD",
    "33642": "06:51:53 V 9 HD",
    "33705": "06.51.55 VỌ HD",
    "33768": "06:51:58 V9 HD",
    "33810": "06:51:59 V9 HD",
    "33845": "12.8fps 06:52:00 9 HD 822",
    "33894": "06:52:02 9 HĐ",
    "33964": "06:52:04 V9 HD",
    "34006": "V9HD 06:52:06",
    "34048": "06:52:07 V9 HD",
    "34125": "06:52:09 V9 HD",
    "34167": "06:52:11 H V 9 HD giây",
    "34230": "06 H 52:13 V9 HD",
    "34258": "06 HTV9 52:14 HD",
    "34300": "06:52:15 V9 HD",
    "34405": "H V9 06:52:19 HD",
    "34426": "06:52:20 V9 HD",
    "34440": "06:52 20 V9 HD",
    "34482": "06:52:21 HD",
    "34559": "06552:24 10 HD",
    "34580": "06:52:25 V9 HD 2 GAL",
    "34629": "06:52:26 H V9 HD",
    "34643": "06:52:27 V9 HD",
    "34678": "H V9 06:52:28 HD",
    "34685": "06:52:28 H V9 HD",
    "34720": "06:52:29 V9 HD",
    "34734": "06.52.30 H V9 HD",
    "34741": "06:52: 30 V9 HD",
    "34755": "06:52:30 H V9 HD NGHỆ MỸ: TRIỂN THUẬT LÃM ĐỂ \"TRÔI CỬU LÂY DẠT ĐAI VÀO DƯƠNG\" BỚ:",
    "34797": "06:52:32 V9 HD giay NGHỆ MỸ: TRIỂN THUẬT LÃM ĐỂ \"TRÔI CỬU LÂY DẠT ĐAI VÀO DƯƠNG\" BỜ:",
    "34811": "06:52 H 32 V9 HD NGHỆ MỸ TRIỂN THUẬT LÃM ĐỂ \"TRÔI CỬU LÂY DẠT ĐẠI VÀO DƯƠNG\" BỜ:",
    "34839": "06:52:33 V9 HD MIO NGHỆ MỸ: TRIỂN THUẬT LÃM ĐỂ \"TRÔI CỬU LÂY DẠT ĐẠI VÀO DƯƠNG\" BỜ:",
    "34909": "THE PLASTIC PROBLEM 06 5236 HD",
    "34930": "PLASTIC PROBLEM HD LEIGH CLAYTON ĐẠI DIÊN THUỶ CUNG NEW YORK",
    "35035": "06:52:40 V 9 HD",
    "35098": "06:52:42 V9 HD",
    "35168": "06.52 44 HD",
    "35175": "0652:44 9 HD",
    "35189": "06:52: 45 9 HD",
    "35196": "06:52 45 V9 HD",
    "35203": "06:52.45 HD",
    "35217": "06-52.46 V 9 HD",
    "35231": "06.52.46 V9 HD",
    "35252": "THE PLASTIC PROBLEM HD",
    "35301": "H V9 06:52 49 HD SHARKSU",
    "35308": "06:52 H 49 V9 HD SHARKSU",
    "35322": "06 H 52 49 V9 HD SHARKS",
    "35329": "06 H 52 50 V9 HD SHARKS",
    "35343": "06:52:50 H V9 HD SHARK C",
    "35357": "06:52:51 H V9 HD SHARK",
    "35385": "06:52: H 51 V9 HD",
    "35455": "06:52:54 V9 HD",
    "35483": "06:52:55 V9 HD",
    "35560": "06:52.57 9 HD",
    "35637": "06:53:00 V 9 HD",
    "35651": "06:53.00 9 HD",
    "35658": "MOTTONATHXMS 06:53:01 V9 HD",
    "35693": "MOTIVE&MAILCOM OS/21 06:53:02 V9 HD STEVE WRIGHT NGHỀ sỉ",
    "35847": "KOTCONARAMES Tituso 06:53:07 V9 HD giay",
    "35854": "MARILYM Lako 06:53:07 V9 HD STEVE&",
    "35896": "MARILYM OS/22) 06:53:09 V9 HD STEVE&",
    "35903": "MARILYM Wuliso 06:53:09 V9 HD STEVE&",
    "35910": "MARILYM OSIZU 06:53:09 V9 HD STEVE&",
    "35931": "06:53-10 V 10 HD",
    "35987": "06:53:12 V 9 HD",
    "36001": "06:53:12 V9 HD",
    "36008": "06:53:12 V 9 HD",
    "36022": "06:53:13 9 HD",
    "36057": "06:53:14 V9 HD",
    "36092": "06:53:15 V9 HD",
    "36099": "- 06:53:15 V9 HD",
    "36120": "06:53:16 H V9 HD",
    "36162": "06:53:17 HT V9 HD",
    "36169": "06-53 VO 8 HD",
    "36232": "06:53 20 V9 HD",
    "36246": "06:53:20 V9 HD",
    "36267": "06: 53:21 V9 HD",
    "36281": "06:53:21 V9 HD",
    "36316": "H V9HD 06:53:23",
    "36330": "06:53:23 H V9 HD",
    "36358": "06:53:24 H V9 HD MARINS SCIR TRIGGERFISH",
    "36428": "06:53:26 H V9 HD MARINE SCIEN",
    "36477": "H V9 06:57:00 HD giây",
    "36540": "06:57:02 H V9 HD",
    "36547": "06:57:03 H V9 HD",
    "36561": "06:57:03 HTV9 HD",
    "36582": "06: HTV9 57:04 HD",
    "36589": "06: HTV9 57:04 HD",
    "36603": "06:57:04 HTV9 HD",
    "36617": "HURBOUR 06:57.05 V9 HĐ DEN HAAG",
    "36645": "06:57: 06 V9 HD DENHAAG",
    "36659": "06:57: H 06 V9 HD DENHAAG",
    "36673": "06:57:07 H V9 HD per CENHAAG",
    "36687": "06:57:07 H V9 HD",
    "36722": "06:57:08 H V9 HĐ",
    "36736": "06.57:09 H V OF HD",
    "36750": "06:57:09 V9 HD",
    "36764": "06:57:10 V9 HD",
    "36778": "06-57:10 H HD",
    "36820": "06:57:12 H V9 HD",
    "36827": "06:57:12 H V9 HD",
    "36834": "06:57 V9 HĐ",
    "36841": "06:57 HD",
    "36855": "06:57:13 HĐ",
    "36862": "06: 57:13 HD",
    "36869": "06:57:13 V9 HD OUR",
    "36876": "06:57:14 V9 HĐ",
    "36890": "06: 57:14 V9 HĐ",
    "36897": "06:57:14 V9 HĐ",
    "36953": "06:57:16 V9 HĐ",
    "36967": "06:57:17 V 9 HĐ",
    "36981": "06:57:17 V 9 HĐ CÁC THÀNH PHỐ TRANG HOÀNG CHUẨN BỊ CHO EURO 2024",
    "37002": "ipoiat 16:574 V 8 HD giáy CÁC THÀNH PHỐ TRANG HOÀNG CHUẨN BỊ CHO EURO 2024",
    "37072": "06:57:20 V9 HD CÁC THÀNH PHỐ TRANG HOÀNG CHUẨN BỊ CHO EURO 2024",
    "37135": "06:57:22 V9 HD",
    "37156": "06:57:23 V9 HD",
    "3717": "H V9HD 06:32:19",
    "37184": "06:57:24 9 HD",
    "37191": "06:57:24 V 9 HD",
    "37198": "06:57:24 V 9 HD",
    "37212": "06:57:25 V 9 HD DANNY NGƯỜI DÂN VAN KHU DIJK PHỐ MARKTWEG HÀ LAN",
    "37324": "06:57:28 V9 HD DANNY VAN DIJK NGƯỜI DÂN KHU PHỐ MARKTWEG HÀ LAN",
    "37366": "06:57:30 V9 HD",
    "37380": "06:57:30 V9 HD",
    "37387": "HHHH 06:57:31 HD HHAR HOOG EAKT OG",
    "37401": "HARAWAHH 06:57:31 HD OG AKT pkic-e",
    "37415": "HAHAHAH 06:57:31 HD EAKT ERKY NL Kichtie Mhi",
    "37422": "V9HD 06:57:32",
    "37436": "06:57:32 V9 HD",
    "37450": "06:57.33 V9 HD ANDEN",
    "37464": "06:57.33 V9 HD ANDE",
    "37471": "06:57: 33 V9 HD",
    "37478": "06:57:34 V9 HD",
    "37485": "06:57:34 V9 HD",
    "37492": "06:57:34 V9 HD",
    "37499": "06:57:34 V9 HD",
    "37513": "06:57:35 V9 HD",
    "37527": "THE 06-57 35 V 9 HD TẠI ID Z E DEN HAAG",
    "37590": "SAN 06:57:37 V9 HD NDA DEN HAAG",
    "37674": "06.57.40 V9 HD WUH ORANJE!",
    "37709": "06:57:41 V9 HD O ORANJE!",
    "3773": "06:32:21 H VI HĐ",
    "37751": "06:57: 43 V9 HD WU HOUDER VAN ORANJE!",
    "37807": "06:57:45 H V9 HĐ eksti",
    "37835": "06:57: 45 HD eksti",
    "37863": "06 57: 46 V 9 HD LMND",
    "37912": "06:57: TV9 48 HD ONI",
    "37919": "06:57: 48 V9 HD N",
    "37933": "06:57: 49 V9 HD",
    "37947": "06:57 49 V9 HD ONI",
    "37961": "06:57: 50 V9 HD ONI",
    "37968": "06:57:50 V 9 HD ON",
    "37982": "06:57: 50 V 9 HD ON",
    "37989": "06:57:51 V9 HD ONI",
    "37996": "10p 06:57:51 9 HD E",
    "38003": "ICe 06:57:51 V 9 HD",
    "38017": "06/57:52 V 9 HD",
    "38031": "06:57:52 HD",
    "38045": "06:57:52 HD",
    "38059": "O 06:57:53 HD YOUR WALK ALONE",
    "38094": "06:57:54 9 HD SAN",
    "38115": "06:57:55 VI HD",
    "38122": "06:57:55 VI HD giây 10",
    "38129": "06:57:55 9 HD Chery",
    "38136": "06:57:56 V9 HD HAMANITY",
    "38171": "06:57:57 V9 HD ANWWWW",
    "38178": "06:57:57 V9 HD WWW.VITY",
    "38199": "06:57: 58 V 9 HD WWWWWWWW.",
    "38206": "06:57:58 9 HD b MAAN",
    "38248": "06:57:59 V 9 HD B WAAN",
    "38262": "06:58:00 V9 HD B MAAN",
    "38269": "06:58:00 V9 HD B MAAN",
    "38276": "06:58:00 V9 HD WWWWWW",
    "38290": "06:58:01 V9 HD WWWWWW",
    "38304": "06:58:01 V9 HD WWWWWW",
    "38318": "06:58:02 V9 HD WWWWWW",
    "38325": "06:58:02 V9 HD WWWWWW",
    "38332": "06:58:02 V9 HD WWWWWW",
    "38346": "06:58:03 V9 HD WWWWWW",
    "38353": "06:58:03 V9 HD WWWWWW",
    "38367": "06:58:03 V 9 HD wwwwww",
    "38374": "06:58:03 V9 HD WWWWWW",
    "38388": "06:58:04 V9 HD WWWWWW",
    "38402": "06:58: 04 V9 HD WWWWWW",
    "38416": "06:58:05 V9 HD ANWWWW",
    "3843": "06:12:23 H 79 HD",
    "38437": "be 06:58: 06 V9 HD O",
    "38451": "B 06:58:06 V9 HD 2",
    "38479": "06:58:07 V9 HD",
    "3850": "06:32:23 VI HD",
    "38521": "06:58: 08 V9 HD",
    "38535": "06:58:09 V9 HD",
    "38549": "06:58:09 V9 HD",
    "38563": "06:58:10 V9 HD",
    "38577": "06:58:10 V9 HD",
    "38591": "06:58:11 V9 HD",
    "38598": "06:58:11 V9 HD",
    "38612": "06:58:11 V9 HD A MAAAI",
    "38619": "06:58:12 V9 HD WAAN",
    "38626": "06:58:12 V9 HD b WAAN",
    "3864": "H VIND 06:32:24 NGHIÊN CỬU MỞ TUYỂN TÀU CAO TỐC TỪ TP. HCM ĐẾN SÂN BAY LONG THÀNH",
    "38640": "06:58:12 V9 HD MAAAI",
    "38654": "06:58:13 V9 HD b MAAAI",
    "38668": "06:58:13 V9 HD",
    "38682": "06:58:14 V9 HD",
    "38696": "06:58:14 V9 HD",
    "38710": "06:58:15 V9 HD",
    "38724": "06.58:15 V9 HD giây",
    "38794": "06:58:17 V9 HD giây",
    "38801": "06:58:18 V9 HD",
    "38864": "06:58:20 V9 HD",
    "38885": "06:58:20 V9 HD",
    "38899": "06:58:21 V9 HD",
    "38913": "06:58:21 V9 HD",
    "38920": "06:58:22 V9 HD",
    "38962": "06:58:23 V9 HD",
    "39004": "06:58:24 V9 HD",
    "39011": "06:58-25 V9 HĐ",
    "39018": "06:58-25 V9 HĐ",
    "39053": "06:58:26 V9 HD",
    "39074": "HadLau 06-58-27 V9 HD Tchally shho The",
    "39081": "MidLass 06-58-27 V9 HD TẬN",
    "39088": "06-58-27 9 HD",
    "39158": "06-58-30 9 HD",
    "39172": "06-58-30 9 HD",
    "39186": "06:58.31 9 HD",
    "39200": "06:58:31 V9 HD 62 TUỔI VÂN CHƠI CỬ TẠ THẬM CHÍ DÀNH NHIÊU HUY CHƯƠNG CHUYÊN NGHIỆP",
    "3927": "06:32:26 H Vi HD 19 NGHIÊN CỬU MỞ TUYỂN TÂU CAO TÓC TỪ TP. HCM ĐẾN SÂN BAY LONG THÀNH",
    "39354": "Syle - 06:58:36 V9 HD GYI",
    "39403": "Tele 06:58:38 V9 HD",
    "39431": "06:58:39 9 HD and sall HisLoue LUYI SALAN byall TWO 21 Disshinh SgpaXity 2uLes slown",
    "39501": "06:58:41 9 HD dụy sall NaiLosa LUYI SALAH Chguinly 33L 21 NAWI 0955 Dặng SUNG 2010 - STOWI",
    "39522": "06.58: 42 V9 HD",
    "39585": "06:58: 44 V9 HD",
    "39592": "06:58 44 V9 HD",
    "39606": "06:58: 45 V9 HD",
    "39620": "06:58: 45 V9 HD",
    "39641": "06:58: 46 V9 HD",
    "39655": "06:58 46 V9 HD",
    "39669": "06:58: 47 V9 HD",
    "39690": "06:58 47 V9 HD",
    "39704": "06.58:48 V 9 HD",
    "39774": "H V9 06.58:50 HĐ",
    "39788": "06:58: 5 V HD",
    "39865": "06:58: 53 V HD AMANY RABIE giáy NỮ VẬN ĐỘNG VIÊN cử TẠ NGƯỜI AI CẬP",
    "39991": "06.58: 57 V HD",
    "39998": "06.58 58 V HD",
    "40012": "06.58 58 V HD",
    "40026": "VIHO 06/58 59",
    "40040": "VIHO 06/58 59",
    "40054": "06.58 59 VI HD",
    "40096": "VIND 06.59:01",
    "40110": "06159 :01 V HD",
    "40124": "06159 02 V HD",
    "40145": "VIHO 06/59 02",
    "40152": "VIFO 06/59 03",
    "40166": "06:59:03 HTV9 HD",
    "40180": "06:59:04 HT V9 HD",
    "40187": "06:59:04 H V9 HD",
    "40229": "06:59:05 V9 HD",
    "40250": "06:59:06 V9 HD",
    "40257": "06:59:06 V9 HD",
    "40271": "06159:07 V9 HD",
    "40292": "06.59:07 V9 HD",
    "40299": "06-59:08 V9 HD",
    "4032": "06:12:29 H VI HD",
    "40320": "06.59:08 V9 THĐ",
    "40334": "06:59 09 V9 HD",
    "40348": "06:59-09 V9 HD",
    "40362": "06.59-10 V9 THD",
    "40376": "06: 59:10 V9 HD",
    "40390": "06:59:11 V 9 HD",
    "40404": "06:59:11 V9 HD",
    "40425": "06:59:12 V9 HD",
    "4046": "V9 06:32:30 GERITAINS",
    "40495": "06:59:14 VO HĐ",
    "40509": "06:59:15 V 10 HĐ",
    "40523": "06:59:15 HĐ",
    "40537": "06:59:16 HĐ",
    "40551": "06:59:16 HĐ",
    "40565": "O 06:59:16 V9 HD",
    "40579": "O 06:59:17 V9 HD",
    "40628": "06:59:19 V9 HD",
    "40649": "TO 06:59:19 H V9 HD NITEDSTATES ON MPIA MONTON YMPIA OWERUE INVITATIONAL POWERLIPTING INVITATIONAL EXPORISTOR TING",
    "40719": "06:59:22 H V9 HD VITEDSTATED OGIATION SMOPICA giãy POWERLIPTINE INVIEATIONAL COFFELERY",
    "40726": "06:59:22 9 HD giãy",
    "40796": "06:59 24 V9 HD giã",
    "4088": "06-32-31 V9 HD",
    "4095": "06:32:31 V 9 HD PHƯƠNG ÁN Vân chuyên hành khachbang tàu cao tóc tư bên tàu Bach Đăng PHƯƠNG AN2 Kết nôi băng hình thức khách ngang song từ BÌNH Khánh PHƯƠNG AN 3 Tăng tốc công suất khai hac phà C atLai",
    "41069": "06:59:33 H V9 HD",
    "4109": "06:32:32 V9 HD PHƯƠNG ÁN 1 Vận chuyên hành khách bằng tàu cao tốc từ bến tàu BẠCH Đằng PHƯƠNG ÁN 2 Kết nối bằng hình thức khách ngang sông từ Bình Khánh PHƯƠNG ÁN 3 Tăng tốc công suât khai thác phà cát Lái",
    "41160": "H V9 06:59:36 HD MỸ MỞ RỘNG CÁC LỆNH TRỪNG PHẠT NHẨM VÀO NGA",
    "41181": "06:59:37 V9 HD MỸ MỞ RỘNG CÁC LỆNH TRỪNG PHẠT NHẨM VÀO NGA",
    "41272": "06:59:40 H V9 HD giay MỸ MỞ RỘNG CÁC LỆNH TRỪNG PHẠT NHẨM VÀO NGA",
    "41314": "06:59:41 H V9 HD",
    "41370": "06:59:43 H V9 HD",
    "41447": "H VIND 06:59:46 EVERGREEN NGO RIGHT SUN MUA",
    "41545": "H V9 06:59 49 HD E1SU3574 635 EVERGREN",
    "41608": "EVERGREN 06:59:51 H V 9 HD AGREEN",
    "41629": "06.59:52 H V9 HD",
    "41685": "06.59.54 H V9 HD",
    "4172": "06:12:14 H V9 HD PHƯƠNG ÁN 1 Vận chuyển hành khách bằng tàu cao tốc từ bến tàu BẠCH Đằng PHƯƠNG ÁN2 Kết nối bằng hình thức khách ngang sông từ Bình Khánh PHƯƠNG ÁN3 Tăng tốc công suất khai thác phà cát Lái",
    "41769": "06:59:57 H V9 HD",
    "41832": "06:59:59 H V9 HD",
    "41909": "GƯO 07:00:01 V9 HD Barkery East 42nd St NGE GROUP +",
    "41979": "07:00: 04 V 9 HD DECO LOWARDS JOSEITI",
    "42049": "V 9 07:00:06 HD",
    "42091": "07:00:07 V9 HD",
    "42126": "07:00:09 V9 HD",
    "42147": "07:00:09 V9 HD",
    "42154": "07:00:09 H V9 HD",
    "42161": "07:00:10 H V9 HD",
    "42168": "07:00:10 H V9 HD",
    "42175": "07:00:10 V9 HD",
    "42210": "07:00:11 V 9 HD",
    "42287": "07.00:14 V9 HD",
    "42329": "07.00:15 H V9 HD",
    "42385": "07:00:17 V9 HD",
    "42469": "07:00:20 HĐ",
    "42518": "07:00:22 H V9 HD",
    "42609": "07:00.25 V9 HD",
    "42679": "H V9 07.00:27 HD giãy",
    "43071": "07:00:40 V9 HD",
    "43155": "07:00:43 V9 HD",
    "43162": "07:00:43 V9 HD",
    "43183": "07:00: 44 V9 HD TẠC ĐARI TRUNG",
    "43190": "07:00:44 V9 HD N TRUNG TÂM TIN TỨC ĐÀI TRƯ",
    "43197": "07:00:44 V9 HD TRUNG TÂM TIALTỨC ĐÀI TRUYỀN HÌNH THÀNH",
    "4347": "06:32:40 H V 9 HD PHƯƠNG ÁN 1 Vận chuyển hành khách bằng tàu cao tốc từ bến tàu BẠCH Đằng PHƯƠNG ÁN 2 Kết nối bằng hình thức khách ngang sông từ Bình Khánh PHƯƠNG ÁN3 Tăng tốc công suất khai thác phà Cát Lái",
    "4662": "06:32:60 VI HĐ PHƯƠNG ÁN 1 Vận chuyển hành khách bằng tàu cao tốc từ bến tàu BẠCH Đàng PHƯƠNG ÁN2 Kết nối bằng hình thức khách ngang sông từ Bình Khánh PHƯƠNG ÁN3 Tăng tốc công suât khai thác phà Cát Lái",
    "4676": "06:32:51 VI HD ben 100P. ong PHUƠI Ket-no DO thữ Tar gloc TẾT suat hainhu phả",
    "4683": "WIND 06:32:51",
    "4746": "VIHO 06:32:53",
    "476": "06:30:25 V9 HD",
    "4823": "H WIHD 06:32:56",
    "483": "06.30 25 V9 HD",
    "4858": "06:12:57 VI HD",
    "49": "06:30.11 HD 100 giậy",
    "490": "VIND 06:3 O",
    "4900": "06:32:58 H VI HD 19",
    "497": "06:30:26 V9 HĐ",
    "5005": "H VIHO 06:33:02",
    "5019": "06:33:02 V9 HD Capanell",
    "504": "06 30:26",
    "5061": "06:33:04 VI HD",
    "511": "06: HTV9 30:26 HD giây TIN CHÍNH",
    "5145": "H VIND 06:33:06",
    "518": "06: 30:26 V 9 HD giây TIN CHÍNH",
    "5222": "06:33:89 H VI HD",
    "5278": "06.33:11 HD giây",
    "5369": "06:33:14 V9 HD",
    "5453": "06 33:17 HD STICHTING LANGEVELDE 1945",
    "546": "06:30:27 V9 HD 16 010 16",
    "5467": "06: 33:17 HĐ S TICHING LANGEVELDE 1945",
    "5516": "06:33:19 H VO HĐ",
    "5558": "06:33:20 H V9 HD",
    "560": "06:30:28 V9 HD 16 010 16 VIETCOMBANK ĐIỀU CHÍNH VIỆC ĐĂNG KÝ MUA VÀNG MIỄNG SJC",
    "5628": "06:33:23 HTV HD",
    "5705": "06:33:25 H TV9 HD",
    "5761": "06:33:27 HD",
    "5789": "06:33:28 H V9 HD",
    "5838": "06:33:30 HD URAKAJI BUÊTHÁU",
    "588": "TIN CHÍNH 06:30/29 H V9 HD VIETCOMBANK ĐIỀU CHÍNH VIỆC ĐĂNG KÝ MUA VÀNG MIỄNG SJC",
    "5887": "CÁO 469 199 06.33:31 V 9 HD FESTIVAL HUẾ 2024 NGÀY HỘI KẾT NỐI BẠN BÈ QUỐC TẾ",
    "5922": "STELTENLOPERS VAN MERCHTEM 06 33:32 9 HD STICHING LANGEVELDE 1945 FESTIVAL HUẾ 2024 NGÀY HỘI KẾT NỐI BẠN BÈ QUỐC TẾ",
    "5943": "STELTENLOPERS VĂN MERCHTEM 06: 33:33 9 HD STICHING LANGEVELDE 1945 FESTIVAL HUẾ 2024 - NGÀY HỘI KẾT NỐI BẠN BÈ QUỐC TẾ",
    "5957": "06 H 33:34 V9 HD giay FESTIVAL HUẾ 2024 NGÀY HỘI KẾT NỐI BẠN BÈ QUỐC TẾ",
    "5999": "06:33 35 VO HD 9 FESTIVAL HUẾ 2024 NGÀY HỘI KẾT NỐI BẠN BÈ QUỐC TẾ",
    "6027": "06:33:36 V9 HD MERCH",
    "6076": "06:33:38 V9 HD R Nghệ sỉ JANICK APPELMANS ĐOÀN NGHÊ THUẬT VƯƠNG QUỐC BÌ",
    "6209": "06:33:42 HD Nghệ sỉ JANICK APPELMANS giay ĐOÀN NGHÊ THUẬT VƯƠNG QUỐC BÌ",
    "6230": "06:33:43 HĐ",
    "6321": "06.33:46 V9 HD MERCH",
    "6433": "06:33:49 V9 HD",
    "644": "TIN CHÍNH 06:30:31 HD VIETCOMBANK ĐIỀU CHÍNH VIỆC ĐĂNG KÝ MUA VÀNG MIỂNG SJC",
    "6503": "06:33:52 V9 HD",
    "6580": "06:33:54 HD",
    "6601": "06.33-55 HĐ Nghệ sỉ MARIANA NETO BRITO LUZ NHÓM HIPHOP THÀNH PHỐ CERGY PHÁP",
    "6755": "06: 34:00 V9 HD",
    "6776": "06:34:01 V9 HD",
    "6825": "06:34:02 V9 HD",
    "6902": "06: 34.05 HĐ",
    "6951": "06:34:07 V9 HD",
    "6993": "06:34:08 V9 HD",
    "7": "06:30-10 VI HD giây",
    "700": "06:30:33 V9 HD",
    "7063": "06.34:10 V9 HD",
    "707": "06:30:33 H V9 HD CÔNG AN QUẢNG NAM BẮT BUÔN BÁN VŨ KHÍ TRÁI PHÉP",
    "7168": "00:00:38 06: 34:14 V9 HD",
    "7182": "00:00:39 06:34:14 V9 HD",
    "7196": "OF ĐƯỜNG PHỐ V N HÓA 06:34:15 NEWS",
    "7210": "ÒNGPHỐ HÓA HÙ 06.34:15 VO HD Ông MOUSSA DIARRA PHÓ CHỦ TỊCH THÀNH PHỐ CERGY PHÁP",
    "7364": "PHỐ HÓA ting 06 34:20",
    "7371": "06: 34:21 9 HD",
    "7413": "06:34:22 9 HD",
    "742": "TIN CHÍNH 06:30:34 9 HD CÔNG AN QUẢNG NAM BẮT BUÔN BÁN VŨ KHÍ TRÁI PHÉP",
    "7469": "06:34:24 V9 HD",
    "7483": "06:34/24 V9 CHD",
    "7497": "/06:34:25 V9 HD",
    "7511": "06: 34:25 V9 HD",
    "7553": "06 34.27 V9 HD",
    "7567": "06 H 34:27 V9 HD",
    "7581": "06: 34:28 V9 HD",
    "7595": "Festry 06:34 28 V9 HD Tr REST FEETINM NGHE GIỆT- GI SAN HOR TIE MENT NHOP PHẤT WITH INTEORATION INTECS",
    "7644": "06:34:30 V9 HD",
    "7812": "06:34:35 V9 HD",
    "791": "TIN CHÍNH 06:30:36 9 HD CÔNG AN QUẢNG NAM BẮT BUÔN BÁN VŨ KHÍ TRÁI PHÉP",
    "8176": "06.34:48 H V9 HD",
    "8253": "06.34.50 H V9 HD",
    "8281": "06.34:51 H V9 HD SẢN SÀNG CHO LIÊN HOAN DU LỊCH BIỂN NHA TRANG 2024",
    "8302": "06:34.52 HD SẢN SÀNG CHO LIÊN HOAN DU LỊCH BIỂN NHA TRANG 2024",
    "8316": "06:34-52 HD NHATRANG TRANG 9 SẢN SÀNG CHO LIÊN HOAN DU LỊCH BIỂN NHA TRANG 2024",
    "8379": "06:34:54 H V9 HD SẢN SÀNG CHO LIÊN HOAN DU LỊCH BIỂN NHA TRANG 2024",
    "8435": "LIEN HOAN DOLỊCH 06:34:56 V9 HD",
    "847": "06:30:37 HD",
    "8498": "ỦY BAN NHÂN LIÊN HOAN DÂN TỈNH DU LỊCH KHÁNH HÒA 06:34:58 V9 HD BIEN NHA TRANG 202 Vinhpane NHATRANG SONG",
    "854": "06:30:38 V9 HD FED TIẾP TỤC GIỮ NGUYÊN LÃI",
    "8547": "06.35:00 H V9 HD",
    "8638": "06:35:03 H VIU HD",
    "8680": "06:35:04 H VI HD BÁ NGUYỄN THI LÊ THANH GIÁM ĐỐC SỞ DU LỊCH KHÁNH HÒA",
    "896": "TIN CHÍNH 06:30:39 V9 HD FED TIẾP TỤC GIỮ NGUYÊN LÃI SUẤT",
    "8960": "06:35:14 VI HD",
    "8995": "06.35:15 HD âM GIAN THỰC HÀNG ĂM GIAN THỰC HÀNG CHAGIO BÁN BOOBIÊT NƯỜNG TOKHUM UiềN HUÔNHOỒ oua BANDADICH OSHỖI",
    "9051": "LANDULICH BIỂN NHÀ TRANG 2024 MÔNG Vinhpage UBNGTÔNH TRADUMÊNTHATÔM KHANH HÒA NHA BungSáng Vinhngi TRANG 06:35: 17 V9 HD NHA NHA LÊNHOME VinhNgoo UBND DOUDI TINH TRANG ĐÊNTHATUNG KHANHHOA INTERNATIONAL BungSang TOWN TRANG GOL INTERNATIONAL TOURISM OCEAN FEST Brang FEST",
    "9093": "Vietravel 06:35:18 V 9 HD",
    "91": "06:30:12 HD 10",
    "9149": "06.35.20 V9 HD",
    "9240": "H V9 06:35:23 HD",
    "9310": "H V9 06.35:25 HD",
    "9366": "06.35:27 H V9 HD",
    "9387": "06:35:28 OF HD",
    "9394": "06.35:28 OF HD",
    "9429": "06-35:29 V 9 HD",
    "9443": "06:35:30 V 9 HD",
    "9485": "06.35:31 H V9 HD BOR",
    "9499": "06.35:32 H V9 HD",
    "952": "SING BELLO JUNE 12 2024 TIN CHÍNH Telefonica 06:30:41 MEM LISTED SE since 1924 NYSE CNB NEW YORK STOCKEXCHANGE FED TIẾP TUC GIỮ NGUYÊN LÃI SUẤT",
    "9625": "06/35:36 H V9 HD",
    "9639": "06:35:36 V9 HD",
    "9674": "06:35:37 V9 HD TY TNHH Fop",
    "9688": "06:35:38 H V9 HD TY TNHH FOCU",
    "9709": "06.35:39 H V9 HD",
    "9793": "06.35:41 H V9 HD",
    "9842": "H V9 06:35:43 HD",
    "9856": "06.35:44 V9 HD",
    "9898": "06:35:45 H V9 HD L",
    "9940": "06:35:46 VI HD",
    "9975": "06:35:47 10 HD HOA LIÊN HOAN DULỊCH"
}